{
    "Enero": {
        "País Vasco": {
            "Precio Gasoleo A": 1.0670097838890535,
            "Precio Gasoleo B": 0.80629136378716,
            "Precio Gasoleo Premium": 1.1331497476122994,
            "Precio Gasolina 95 E5": 1.1111271339436442,
            "Precio Gasolina 98 E5": 1.2330749872044928,
            "Precio Biodiesel": 1.0667477956989249,
            "Precio Bioetanol": 1.3225591397849465,
            "Precio Gases licuados del petróleo": 0.6093297135801382
        },
        "Castilla la Mancha": {
            "Precio Gasoleo A": 1.0921220971085814,
            "Precio Gasoleo B": 0.7702311864188348,
            "Precio Gasolina 95 E5": 1.1458933321077633,
            "Precio Gasoleo Premium": 1.1639031097031112,
            "Precio Gasolina 98 E5": 1.2702118086182062,
            "Precio Gases licuados del petróleo": 0.6128955008488965,
            "Precio Biodiesel": 1.0517258064516135,
            "Precio Gas Natural Comprimido": 0.9370000000000004
        },
        "Comunidad Valenciana": {
            "Precio Gasoleo A": 1.072750804651583,
            "Precio Gasoleo Premium": 1.1439648795275768,
            "Precio Gasolina 95 E5": 1.1373661090917688,
            "Precio Gasolina 98 E5": 1.2660458673163502,
            "Precio Gasoleo B": 0.7917859979064106,
            "Precio Gases licuados del petróleo": 0.6071717266972531,
            "Precio Biodiesel": 1.0944826164874542,
            "Precio Gas Natural Comprimido": 0.9444838709677412,
            "Precio Bioetanol": 1.2503225806451614
        },
        "Andalucia": {
            "Precio Gasoleo A": 1.0898477526468209,
            "Precio Gasoleo B": 0.7735769086785386,
            "Precio Gasoleo Premium": 1.1599174992262935,
            "Precio Gasolina 95 E5": 1.15391657824695,
            "Precio Gasolina 98 E5": 1.2798566204553798,
            "Precio Gases licuados del petróleo": 0.6134407270007864,
            "Precio Biodiesel": 1.1435363955119204
        },
        "Castilla y León": {
            "Precio Gasoleo A": 1.075702330874506,
            "Precio Gasoleo B": 0.7955845711251621,
            "Precio Gasoleo Premium": 1.1435187830020612,
            "Precio Gasolina 95 E5": 1.1170700113069354,
            "Precio Gasolina 98 E5": 1.239896069852209,
            "Precio Gases licuados del petróleo": 0.6153635235732009,
            "Precio Biodiesel": 1.1150148883374689,
            "Precio Bioetanol": 1.2469999999999997
        },
        "Extremadura": {
            "Precio Gasoleo A": 1.0989761999028815,
            "Precio Gasoleo B": 0.7915191738531041,
            "Precio Gasoleo Premium": 1.1696439544685244,
            "Precio Gasolina 95 E5": 1.1489336465952318,
            "Precio Gasolina 98 E5": 1.2872073551328602,
            "Precio Gases licuados del petróleo": 0.6032811059907833,
            "Precio Biodiesel": 1.1334946236559138
        },
        "Baleares": {
            "Precio Gasoleo A": 1.136039942512603,
            "Precio Gasoleo Premium": 1.19489393939394,
            "Precio Gasolina 95 E5": 1.1883872887864828,
            "Precio Gasolina 98 E5": 1.3053330552465703,
            "Precio Gases licuados del petróleo": 0.6036686217008798,
            "Precio Gasoleo B": 0.8280087183958154
        },
        "Cataluña": {
            "Precio Gasoleo A": 1.0696168511411188,
            "Precio Gasoleo Premium": 1.1469343135751595,
            "Precio Gasolina 95 E5": 1.1321770073868336,
            "Precio Gasolina 98 E5": 1.262471099756969,
            "Precio Gases licuados del petróleo": 0.5937267864490429,
            "Precio Gasoleo B": 0.7821345927115371,
            "Precio Biodiesel": 1.0751915138450605,
            "Precio Bioetanol": 1.3820000000000001,
            "Precio Gas Natural Comprimido": 0.8898951612903221
        },
        "Galicia": {
            "Precio Gases licuados del petróleo": 0.6344843317972351,
            "Precio Gasoleo A": 1.119317734636779,
            "Precio Gasoleo B": 0.8125794507003867,
            "Precio Gasoleo Premium": 1.1871619634122206,
            "Precio Gasolina 98 E5": 1.289936910270692,
            "Precio Gasolina 95 E5": 1.1656966133068056,
            "Precio Biodiesel": 1.1286272401433686,
            "Precio Bioetanol": 1.2256206896551731
        },
        "Aragón": {
            "Precio Gasoleo A": 1.042846871804974,
            "Precio Gasoleo B": 0.7367339875838045,
            "Precio Gasoleo Premium": 1.1212898090864374,
            "Precio Gasolina 95 E5": 1.102194227055018,
            "Precio Gasolina 98 E5": 1.2316364821393908,
            "Precio Biodiesel": 1.0218947132616483,
            "Precio Gases licuados del petróleo": 0.6050434017595305
        },
        "Rioja (La)": {
            "Precio Gasoleo A": 1.0626603985976517,
            "Precio Gasoleo B": 0.800942614074427,
            "Precio Gasoleo Premium": 1.1353181530676788,
            "Precio Gasolina 95 E5": 1.1089043262947933,
            "Precio Gasolina 98 E5": 1.2328992505702185,
            "Precio Biodiesel": 1.0215645161290319,
            "Precio Gases licuados del petróleo": 0.6472473118279571
        },
        "Madrid": {
            "Precio Gases licuados del petróleo": 0.6067552240723614,
            "Precio Gasoleo A": 1.0615714108458278,
            "Precio Gasoleo B": 0.7974295702518543,
            "Precio Gasoleo Premium": 1.1259128968230332,
            "Precio Gasolina 95 E5": 1.1177759131932075,
            "Precio Gasolina 98 E5": 1.2431878427765917,
            "Precio Biodiesel": 1.0997580645161287,
            "Precio Bioetanol": 1.1554354838709675
        },
        "Murcia": {
            "Precio Gasoleo A": 1.0699596255474537,
            "Precio Gasoleo B": 0.8014377558555944,
            "Precio Gasoleo Premium": 1.1416232280701488,
            "Precio Gasolina 95 E5": 1.1386198253710242,
            "Precio Gasolina 98 E5": 1.263925204890058,
            "Precio Gases licuados del petróleo": 0.6062752688172043,
            "Precio Biodiesel": 1.0603225806451608
        },
        "Navarra": {
            "Precio Gasoleo A": 1.037101809809901,
            "Precio Gasoleo B": 0.7367064329299176,
            "Precio Gasoleo Premium": 1.1266472394722213,
            "Precio Gasolina 95 E5": 1.0973232536528568,
            "Precio Gasolina 98 E5": 1.2332366435348712,
            "Precio Biodiesel": 1.0321794721407624,
            "Precio Gases licuados del petróleo": 0.6380238095238093,
            "Precio Bioetanol": 1.25
        },
        "Asturias": {
            "Precio Gasoleo A": 1.102305560557405,
            "Precio Gasoleo B": 0.8071772944381086,
            "Precio Gasoleo Premium": 1.1684788572893312,
            "Precio Gasolina 95 E5": 1.1634497950357638,
            "Precio Gasolina 98 E5": 1.282587528715194,
            "Precio Biodiesel": 1.0777903225806453,
            "Precio Gases licuados del petróleo": 0.6128774193548385,
            "Precio Bioetanol": 1.2389999999999999
        },
        "Canarias": {
            "Precio Gasoleo A": 0.8890032586370834,
            "Precio Gasolina 95 E5": 0.921310365411689,
            "Precio Gasolina 98 E5": 1.0149048384996082,
            "Precio Gasoleo Premium": 0.9502889478984773,
            "Precio Gases licuados del petróleo": 0.4589774193548386
        },
        "Cantabria": {
            "Precio Gasoleo A": 1.0641977013484136,
            "Precio Gasoleo B": 0.8322259897360704,
            "Precio Gasoleo Premium": 1.1311042731755874,
            "Precio Gasolina 95 E5": 1.1124206248412498,
            "Precio Gasolina 98 E5": 1.2366576841536412,
            "Precio Biodiesel": 1.1340591397849458,
            "Precio Gases licuados del petróleo": 0.636858064516129
        },
        "Ceuta": {
            "Precio Gasoleo A": 0.9385698924731186,
            "Precio Gasolina 95 E5": 1.0015017921146956,
            "Precio Gasolina 98 E5": 1.029247311827957,
            "Precio Gasoleo Premium": 0.9736370967741931
        },
        "Melilla": {
            "Precio Gasoleo A": 0.869843672456576,
            "Precio Gasoleo Premium": 0.9202451612903226,
            "Precio Gasolina 95 E5": 0.9250545905707199
        }
    },
    "Febrero": {
        "País Vasco": {
            "Precio Gasoleo A": 1.1441822048458794,
            "Precio Gasoleo B": 0.8728165236549162,
            "Precio Gasoleo Premium": 1.2129322028065181,
            "Precio Gasolina 95 E5": 1.1969018012709305,
            "Precio Gasolina 98 E5": 1.3195636738095857,
            "Precio Biodiesel": 1.1326157142857143,
            "Precio Bioetanol": 1.3347261904761911,
            "Precio Gases licuados del petróleo": 0.6129786255411254
        },
        "Castilla la Mancha": {
            "Precio Gasoleo A": 1.157453516813162,
            "Precio Gasoleo B": 0.8041818824345949,
            "Precio Gasolina 95 E5": 1.2209687691609346,
            "Precio Gasoleo Premium": 1.2333110155521692,
            "Precio Gasolina 98 E5": 1.3460542931376724,
            "Precio Gases licuados del petróleo": 0.6186051638837354,
            "Precio Biodiesel": 1.1381249999999992,
            "Precio Gas Natural Comprimido": 0.9370000000000003
        },
        "Comunidad Valenciana": {
            "Precio Gasoleo A": 1.1383449147117255,
            "Precio Gasoleo Premium": 1.2126844214791306,
            "Precio Gasolina 95 E5": 1.2109921818878873,
            "Precio Gasolina 98 E5": 1.3385756850783639,
            "Precio Gasoleo B": 0.821961874900796,
            "Precio Gases licuados del petróleo": 0.6109810267857141,
            "Precio Biodiesel": 1.1119472222222224,
            "Precio Gas Natural Comprimido": 0.8790000000000006,
            "Precio Bioetanol": 1.3282500000000002
        },
        "Andalucia": {
            "Precio Gasoleo A": 1.1571224461801581,
            "Precio Gasoleo B": 0.8136675146843866,
            "Precio Gasoleo Premium": 1.2305272777747363,
            "Precio Gasolina 95 E5": 1.2302504192570107,
            "Precio Gasolina 98 E5": 1.3560641762694812,
            "Precio Gases licuados del petróleo": 0.6171309948979589,
            "Precio Biodiesel": 1.1731590909090908
        },
        "Castilla y León": {
            "Precio Gasoleo A": 1.1457950094582767,
            "Precio Gasoleo B": 0.8400664061102925,
            "Precio Gasoleo Premium": 1.2159525712988644,
            "Precio Gasolina 95 E5": 1.1965816509906833,
            "Precio Gasolina 98 E5": 1.3188215294288699,
            "Precio Gases licuados del petróleo": 0.6195443884818888,
            "Precio Biodiesel": 1.157236263736264
        },
        "Extremadura": {
            "Precio Gasoleo A": 1.1565383289925528,
            "Precio Gasoleo B": 0.810070561219207,
            "Precio Gasoleo Premium": 1.2306929668870323,
            "Precio Gasolina 95 E5": 1.2196744568868443,
            "Precio Gasolina 98 E5": 1.352084149614363,
            "Precio Gases licuados del petróleo": 0.6126031746031744,
            "Precio Biodiesel": 1.1741190476190482
        },
        "Baleares": {
            "Precio Gasoleo A": 1.2151959954562128,
            "Precio Gasoleo Premium": 1.27287506196094,
            "Precio Gasolina 95 E5": 1.2826781381763097,
            "Precio Gasolina 98 E5": 1.3996137845511767,
            "Precio Gases licuados del petróleo": 0.6119155844155848,
            "Precio Gasoleo B": 0.8812384169884171
        },
        "Cataluña": {
            "Precio Gasoleo A": 1.1343487934602432,
            "Precio Gasoleo Premium": 1.2173154951982086,
            "Precio Gasolina 95 E5": 1.2041190031997533,
            "Precio Gasolina 98 E5": 1.3373599346854714,
            "Precio Gases licuados del petróleo": 0.5956466283832672,
            "Precio Gasoleo B": 0.8207807780671937,
            "Precio Biodiesel": 1.1204737565066518,
            "Precio Bioetanol": 1.3820000000000003,
            "Precio Gas Natural Comprimido": 0.8730000000000006
        },
        "Galicia": {
            "Precio Gases licuados del petróleo": 0.6307057823129253,
            "Precio Gasoleo A": 1.1876686229386417,
            "Precio Gasoleo B": 0.8587364076977636,
            "Precio Gasoleo Premium": 1.2549187365937393,
            "Precio Gasolina 98 E5": 1.3669192294214516,
            "Precio Gasolina 95 E5": 1.247164071260126,
            "Precio Biodiesel": 1.1660436507936516,
            "Precio Bioetanol": 1.2695416666666677
        },
        "Aragón": {
            "Precio Gasoleo A": 1.1079573862877379,
            "Precio Gasoleo B": 0.7804312625776619,
            "Precio Gasoleo Premium": 1.1958665847031473,
            "Precio Gasolina 95 E5": 1.176668153978183,
            "Precio Gasolina 98 E5": 1.3124559417950474,
            "Precio Biodiesel": 1.0664563492063495,
            "Precio Gases licuados del petróleo": 0.6025948051948055
        },
        "Rioja (La)": {
            "Precio Gasoleo A": 1.1356468597298068,
            "Precio Gasoleo B": 0.8432576530612241,
            "Precio Gasoleo Premium": 1.2127983193277314,
            "Precio Gasolina 95 E5": 1.1926156716417913,
            "Precio Gasolina 98 E5": 1.3188642857142856,
            "Precio Biodiesel": 1.0832142857142857,
            "Precio Gases licuados del petróleo": 0.6162023809523809
        },
        "Madrid": {
            "Precio Gases licuados del petróleo": 0.6130417588982864,
            "Precio Gasoleo A": 1.1307374320971066,
            "Precio Gasoleo B": 0.8531219919786095,
            "Precio Gasoleo Premium": 1.1951235553945723,
            "Precio Gasolina 95 E5": 1.1939604500147483,
            "Precio Gasolina 98 E5": 1.3157557804963516,
            "Precio Biodiesel": 1.1690803571428572,
            "Precio Bioetanol": 1.2226071428571426
        },
        "Murcia": {
            "Precio Gasoleo A": 1.1373710362757226,
            "Precio Gasoleo B": 0.8363277596500153,
            "Precio Gasoleo Premium": 1.2106499613143207,
            "Precio Gasolina 95 E5": 1.2116451387077312,
            "Precio Gasolina 98 E5": 1.3350923987853733,
            "Precio Gases licuados del petróleo": 0.5837,
            "Precio Biodiesel": 1.1095238095238094
        },
        "Navarra": {
            "Precio Gasoleo A": 1.0953500963071565,
            "Precio Gasoleo B": 0.7704408727359752,
            "Precio Gasoleo Premium": 1.1926416859196505,
            "Precio Gasolina 95 E5": 1.1643750903617247,
            "Precio Gasolina 98 E5": 1.3028017180925662,
            "Precio Biodiesel": 1.0826905122655124,
            "Precio Gases licuados del petróleo": 0.6297959183673469,
            "Precio Bioetanol": 1.25
        },
        "Asturias": {
            "Precio Gasoleo A": 1.1719912446853258,
            "Precio Gasoleo B": 0.8512243003127248,
            "Precio Gasoleo Premium": 1.2394053311043893,
            "Precio Gasolina 95 E5": 1.2445317599552843,
            "Precio Gasolina 98 E5": 1.3634648051273381,
            "Precio Gases licuados del petróleo": 0.6164714285714286,
            "Precio Bioetanol": 1.3086428571428572,
            "Precio Biodiesel": 1.1417500000000003
        },
        "Canarias": {
            "Precio Gasoleo A": 0.8810600310477159,
            "Precio Gasolina 95 E5": 0.9125310909056655,
            "Precio Gasolina 98 E5": 1.0064195780449827,
            "Precio Gasoleo Premium": 0.944486064118407,
            "Precio Gases licuados del petróleo": 0.461992261904762
        },
        "Cantabria": {
            "Precio Gasoleo A": 1.1317304878044756,
            "Precio Gasoleo B": 0.8400998669005725,
            "Precio Gasoleo Premium": 1.201930934702611,
            "Precio Gasolina 95 E5": 1.1873224556790896,
            "Precio Gasolina 98 E5": 1.3045360291785415,
            "Precio Biodiesel": 1.1807261904761905,
            "Precio Gases licuados del petróleo": 0.6308125000000001
        },
        "Ceuta": {
            "Precio Gasoleo A": 0.9159642857142865,
            "Precio Gasolina 95 E5": 0.973801587301588,
            "Precio Gasolina 98 E5": 1.0010793650793652,
            "Precio Gasoleo Premium": 0.9483749999999999
        },
        "Melilla": {
            "Precio Gasoleo A": 0.846836538461539,
            "Precio Gasoleo Premium": 0.8981357142857147,
            "Precio Gasolina 95 E5": 0.8956826923076918
        }
    },
    "Marzo": {
        "País Vasco": {
            "Precio Gasoleo A": 1.1616967534427256,
            "Precio Gasoleo B": 0.8912240992878094,
            "Precio Gasoleo Premium": 1.2288103456577217,
            "Precio Gasolina 95 E5": 1.2489496844341639,
            "Precio Gasolina 98 E5": 1.37047465643018,
            "Precio Biodiesel": 1.1500143548387098,
            "Precio Bioetanol": 1.3422903225806446,
            "Precio Gases licuados del petróleo": 0.6507257918799296
        },
        "Castilla la Mancha": {
            "Precio Gasoleo A": 1.1856952179383655,
            "Precio Gasoleo B": 0.8326685791154814,
            "Precio Gasolina 95 E5": 1.2781071947783367,
            "Precio Gasoleo Premium": 1.2579952358586097,
            "Precio Gasolina 98 E5": 1.401537142642594,
            "Precio Gases licuados del petróleo": 0.6548841642228738,
            "Precio Gas Natural Comprimido": 0.9370000000000004,
            "Precio Biodiesel": 1.1802903225806454
        },
        "Comunidad Valenciana": {
            "Precio Gasoleo A": 1.1747042485188688,
            "Precio Gasoleo Premium": 1.249678894166206,
            "Precio Gasolina 95 E5": 1.2742864630065494,
            "Precio Gasolina 98 E5": 1.4019232122420795,
            "Precio Gasoleo B": 0.853795873381532,
            "Precio Gases licuados del petróleo": 0.6521612903225803,
            "Precio Biodiesel": 1.1463010752688174,
            "Precio Gas Natural Comprimido": 0.8590000000000007,
            "Precio Bioetanol": 1.381774193548387
        },
        "Andalucia": {
            "Precio Gasoleo A": 1.1867903593130638,
            "Precio Gasoleo B": 0.8449252012698697,
            "Precio Gasoleo Premium": 1.2580030124621293,
            "Precio Gasolina 95 E5": 1.2881864647516335,
            "Precio Gasolina 98 E5": 1.411868843285089,
            "Precio Gases licuados del petróleo": 0.6532162651864256,
            "Precio Biodiesel": 1.1889528879255384
        },
        "Castilla y León": {
            "Precio Gasoleo A": 1.1667381921763897,
            "Precio Gasoleo B": 0.8666216851280334,
            "Precio Gasoleo Premium": 1.235467273973837,
            "Precio Gasolina 95 E5": 1.248087349669852,
            "Precio Gasolina 98 E5": 1.3700297991195622,
            "Precio Gases licuados del petróleo": 0.6574832735961766,
            "Precio Biodiesel": 1.1761736972704713
        },
        "Extremadura": {
            "Precio Gasoleo A": 1.1859635237364383,
            "Precio Gasoleo B": 0.8339498217134385,
            "Precio Gasoleo Premium": 1.2575791830522647,
            "Precio Gasolina 95 E5": 1.276825934804324,
            "Precio Gasolina 98 E5": 1.4027713566513687,
            "Precio Gases licuados del petróleo": 0.6507211981566822,
            "Precio Biodiesel": 1.192935483870968
        },
        "Baleares": {
            "Precio Gasoleo A": 1.24347431302237,
            "Precio Gasoleo Premium": 1.3018234993275628,
            "Precio Gasolina 95 E5": 1.3479315251429824,
            "Precio Gasolina 98 E5": 1.465819883149541,
            "Precio Gases licuados del petróleo": 0.6498299120234603,
            "Precio Gasoleo B": 0.9092911944202271
        },
        "Cataluña": {
            "Precio Gasoleo A": 1.1695314819532516,
            "Precio Gasoleo Premium": 1.2500914275462653,
            "Precio Gasolina 95 E5": 1.2653163556260383,
            "Precio Gasolina 98 E5": 1.397552280902604,
            "Precio Gases licuados del petróleo": 0.6317580272340384,
            "Precio Gasoleo B": 0.8528641045663194,
            "Precio Biodiesel": 1.1529575116451176,
            "Precio Bioetanol": 1.3820000000000001,
            "Precio Gas Natural Comprimido": 0.870379032258065
        },
        "Galicia": {
            "Precio Gases licuados del petróleo": 0.6587313664596267,
            "Precio Gasoleo A": 1.2086071668422063,
            "Precio Gasoleo B": 0.881413269455028,
            "Precio Gasoleo Premium": 1.2754165931847585,
            "Precio Gasolina 98 E5": 1.4172165891224986,
            "Precio Gasolina 95 E5": 1.2994975217267888,
            "Precio Biodiesel": 1.1865878136200714,
            "Precio Bioetanol": 1.309
        },
        "Aragón": {
            "Precio Gasoleo A": 1.1375465055810674,
            "Precio Gasoleo B": 0.812353085962485,
            "Precio Gasoleo Premium": 1.2206301008969542,
            "Precio Gasolina 95 E5": 1.234067697374143,
            "Precio Gasolina 98 E5": 1.3661755179588384,
            "Precio Biodiesel": 1.1052544802867381,
            "Precio Gases licuados del petróleo": 0.6415445747800589
        },
        "Rioja (La)": {
            "Precio Gasoleo A": 1.153455092499833,
            "Precio Gasoleo B": 0.8661405529953916,
            "Precio Gasoleo Premium": 1.227401644528779,
            "Precio Gasolina 95 E5": 1.2400621379904004,
            "Precio Gasolina 98 E5": 1.3643161290322579,
            "Precio Biodiesel": 1.088806451612904,
            "Precio Gases licuados del petróleo": 0.6501612903225806
        },
        "Madrid": {
            "Precio Gases licuados del petróleo": 0.6557148379576613,
            "Precio Gasoleo A": 1.1680502316836274,
            "Precio Gasoleo B": 0.8833473761572078,
            "Precio Gasoleo Premium": 1.2310636576004161,
            "Precio Gasolina 95 E5": 1.2573097802192306,
            "Precio Gasolina 98 E5": 1.37846660734341,
            "Precio Biodiesel": 1.2001532258064516,
            "Precio Bioetanol": 1.2800967741935474
        },
        "Murcia": {
            "Precio Gasoleo A": 1.171214611599075,
            "Precio Gasoleo B": 0.858767989285911,
            "Precio Gasoleo Premium": 1.2437708520226944,
            "Precio Gasolina 95 E5": 1.2725869420365927,
            "Precio Gasolina 98 E5": 1.3931559168019738,
            "Precio Gases licuados del petróleo": 0.6142327956989246,
            "Precio Biodiesel": 1.1346666666666667
        },
        "Navarra": {
            "Precio Gasoleo A": 1.12405576618798,
            "Precio Gasoleo B": 0.8027778640592851,
            "Precio Gasoleo Premium": 1.2116549923195077,
            "Precio Gasolina 95 E5": 1.2172761003472234,
            "Precio Gasolina 98 E5": 1.3476441207075964,
            "Precio Biodiesel": 1.1180161290322577,
            "Precio Gases licuados del petróleo": 0.6415622119815668,
            "Precio Bioetanol": 1.25
        },
        "Asturias": {
            "Precio Gasoleo A": 1.1947773318405288,
            "Precio Gasoleo B": 0.879653726554119,
            "Precio Gasoleo Premium": 1.2612444352632632,
            "Precio Gasolina 95 E5": 1.294433961432801,
            "Precio Gasolina 98 E5": 1.412585458943249,
            "Precio Biodiesel": 1.1764999999999999,
            "Precio Gases licuados del petróleo": 0.6530903225806451,
            "Precio Bioetanol": 1.3986774193548395
        },
        "Canarias": {
            "Precio Gasoleo A": 0.9175362532237387,
            "Precio Gasolina 95 E5": 0.952131971755815,
            "Precio Gasolina 98 E5": 1.04718379545682,
            "Precio Gasoleo Premium": 0.9821684377228665,
            "Precio Gases licuados del petróleo": 0.48826881720430104
        },
        "Cantabria": {
            "Precio Gasoleo A": 1.1587824287196427,
            "Precio Gasoleo B": 0.866534957075963,
            "Precio Gasoleo Premium": 1.2271250712234678,
            "Precio Gasolina 95 E5": 1.243326804508177,
            "Precio Gasolina 98 E5": 1.3592080995563995,
            "Precio Biodiesel": 1.204389247311828,
            "Precio Gases licuados del petróleo": 0.6508892473118283
        },
        "Ceuta": {
            "Precio Gasoleo A": 0.9267777777777786,
            "Precio Gasolina 95 E5": 0.9847777777777784,
            "Precio Gasolina 98 E5": 1.0127777777777778,
            "Precio Gasoleo Premium": 0.9589999999999997
        },
        "Melilla": {
            "Precio Gasoleo A": 0.8590000000000007,
            "Precio Gasoleo Premium": 0.9107741935483865,
            "Precio Gasolina 95 E5": 0.9089999999999997
        }
    },
    "Abril": {
        "País Vasco": {
            "Precio Gasoleo A": 1.168681468146651,
            "Precio Gasoleo B": 0.8976610930735929,
            "Precio Gasoleo Premium": 1.2364778233462443,
            "Precio Gasolina 95 E5": 1.2724587930886935,
            "Precio Gasolina 98 E5": 1.3943499068224015,
            "Precio Biodiesel": 1.1572013333333333,
            "Precio Bioetanol": 1.347361111111111,
            "Precio Gases licuados del petróleo": 0.6468659765355421
        },
        "Castilla la Mancha": {
            "Precio Gasoleo A": 1.1909045686717354,
            "Precio Gasoleo B": 0.8399512600666859,
            "Precio Gasolina 95 E5": 1.2976404474347345,
            "Precio Gasoleo Premium": 1.2650603275411394,
            "Precio Gasolina 98 E5": 1.420959064189191,
            "Precio Gases licuados del petróleo": 0.6573164806763282,
            "Precio Gas Natural Comprimido": 0.9428000000000004,
            "Precio Biodiesel": 1.1826999999999999
        },
        "Comunidad Valenciana": {
            "Precio Gasoleo A": 1.1818789045127276,
            "Precio Gasoleo Premium": 1.2578102578790764,
            "Precio Gasolina 95 E5": 1.2954467962466347,
            "Precio Gasolina 98 E5": 1.4246787496883795,
            "Precio Gasoleo B": 0.8585902574266826,
            "Precio Gases licuados del petróleo": 0.6526708333333333,
            "Precio Biodiesel": 1.1621345238095235,
            "Precio Gas Natural Comprimido": 0.8590000000000005,
            "Precio Bioetanol": 1.3874999999999993
        },
        "Andalucia": {
            "Precio Gasoleo A": 1.1934294760818622,
            "Precio Gasoleo B": 0.8504800338775242,
            "Precio Gasoleo Premium": 1.2661351239171343,
            "Precio Gasolina 95 E5": 1.3088233165924046,
            "Precio Gasolina 98 E5": 1.4330954399947016,
            "Precio Gases licuados del petróleo": 0.6529895505371651,
            "Precio Biodiesel": 1.187128679653679
        },
        "Castilla y León": {
            "Precio Gasoleo A": 1.171678531668915,
            "Precio Gasoleo Premium": 1.2412345536879212,
            "Precio Gasolina 95 E5": 1.2700838771433378,
            "Precio Gasolina 98 E5": 1.3910192840099709,
            "Precio Gasoleo B": 0.8717995437469421,
            "Precio Gases licuados del petróleo": 0.6556441707717569,
            "Precio Biodiesel": 1.1688769230769236
        },
        "Extremadura": {
            "Precio Gasoleo A": 1.1800850684515207,
            "Precio Gasoleo B": 0.8365146298405192,
            "Precio Gasoleo Premium": 1.2530060387355,
            "Precio Gasolina 95 E5": 1.287057361020625,
            "Precio Gasolina 98 E5": 1.4131820216848647,
            "Precio Gases licuados del petróleo": 0.6474809523809524,
            "Precio Biodiesel": 1.187911111111111
        },
        "Baleares": {
            "Precio Gasoleo A": 1.25255117399292,
            "Precio Gasoleo Premium": 1.3126878670334172,
            "Precio Gasolina 95 E5": 1.3772748847609215,
            "Precio Gasolina 98 E5": 1.4970409482758622,
            "Precio Gases licuados del petróleo": 0.6618909090909091,
            "Precio Gasoleo B": 0.9093171171171172
        },
        "Cataluña": {
            "Precio Gasoleo A": 1.1774452838302765,
            "Precio Gasoleo Premium": 1.2589668895398305,
            "Precio Gasolina 95 E5": 1.2871332563430506,
            "Precio Gasolina 98 E5": 1.4207743485582698,
            "Precio Gases licuados del petróleo": 0.6312906350597165,
            "Precio Gasoleo B": 0.8574343629273193,
            "Precio Biodiesel": 1.155385582546109,
            "Precio Bioetanol": 1.3820000000000003,
            "Precio Gas Natural Comprimido": 0.8867499999999995
        },
        "Galicia": {
            "Precio Gases licuados del petróleo": 0.6580989444444444,
            "Precio Gasoleo A": 1.214908117810498,
            "Precio Gasoleo B": 0.8883896303025928,
            "Precio Gasoleo Premium": 1.281984160554363,
            "Precio Gasolina 98 E5": 1.4430837186360082,
            "Precio Gasolina 95 E5": 1.3241380629929687,
            "Precio Biodiesel": 1.1893962962962965,
            "Precio Bioetanol": 1.3518571428571426
        },
        "Aragón": {
            "Precio Gasoleo A": 1.1422561820310984,
            "Precio Gasoleo B": 0.8171392712050172,
            "Precio Gasoleo Premium": 1.2276961926773462,
            "Precio Gasolina 95 E5": 1.2549453531133492,
            "Precio Gasolina 98 E5": 1.385574937868184,
            "Precio Biodiesel": 1.1062592592592593,
            "Precio Gases licuados del petróleo": 0.6381745454545459
        },
        "Rioja (La)": {
            "Precio Gasoleo A": 1.1594900169395819,
            "Precio Gasoleo B": 0.8722391703975034,
            "Precio Gasoleo Premium": 1.235794747765773,
            "Precio Gasolina 95 E5": 1.2625458336025503,
            "Precio Gasolina 98 E5": 1.385500252525252,
            "Precio Biodiesel": 1.0932,
            "Precio Gases licuados del petróleo": 0.6464000000000004
        },
        "Madrid": {
            "Precio Gases licuados del petróleo": 0.6555836496850361,
            "Precio Gasoleo A": 1.176396176431541,
            "Precio Gasoleo B": 0.8908840240641711,
            "Precio Gasoleo Premium": 1.2393435571769091,
            "Precio Gasolina 95 E5": 1.2778720941133948,
            "Precio Gasolina 98 E5": 1.3999629970549885,
            "Precio Biodiesel": 1.2129083333333335,
            "Precio Bioetanol": 1.3059000000000003
        },
        "Murcia": {
            "Precio Gasoleo A": 1.179682885169219,
            "Precio Gasoleo B": 0.8652334474423417,
            "Precio Gasolina 95 E5": 1.2933834321300473,
            "Precio Gasolina 98 E5": 1.4157029813508735,
            "Precio Gasoleo Premium": 1.253868065093275,
            "Precio Gases licuados del petróleo": 0.6274899999999995,
            "Precio Biodiesel": 1.1744444444444442
        },
        "Navarra": {
            "Precio Gasoleo A": 1.1258862563956873,
            "Precio Gasoleo B": 0.8078782635427667,
            "Precio Gasoleo Premium": 1.2161958177756753,
            "Precio Gasolina 95 E5": 1.243981448658859,
            "Precio Gasolina 98 E5": 1.3729723036365742,
            "Precio Gases licuados del petróleo": 0.6412182539682537,
            "Precio Biodiesel": 1.1176788888888889,
            "Precio Bioetanol": 1.25
        },
        "Asturias": {
            "Precio Gasoleo A": 1.2030302929980563,
            "Precio Gasoleo B": 0.8865787679777208,
            "Precio Gasoleo Premium": 1.2696328718286438,
            "Precio Gasolina 95 E5": 1.3166111240182532,
            "Precio Gasolina 98 E5": 1.4357293074148418,
            "Precio Biodiesel": 1.184983333333334,
            "Precio Gases licuados del petróleo": 0.6529587878787878,
            "Precio Bioetanol": 1.4260000000000008
        },
        "Canarias": {
            "Precio Gasoleo A": 0.9214575598008992,
            "Precio Gasolina 95 E5": 0.9763857879873201,
            "Precio Gasolina 98 E5": 1.073463518767751,
            "Precio Gasoleo Premium": 0.9854189640581076,
            "Precio Gases licuados del petróleo": 0.5019687301587302
        },
        "Cantabria": {
            "Precio Gasoleo A": 1.1647771333137733,
            "Precio Gasoleo B": 0.8705190839850119,
            "Precio Gasoleo Premium": 1.2347655222132456,
            "Precio Gasolina 95 E5": 1.268183753236205,
            "Precio Gasolina 98 E5": 1.3842318294578184,
            "Precio Biodiesel": 1.2045555555555556,
            "Precio Gases licuados del petróleo": 0.6514566666666666
        },
        "Ceuta": {
            "Precio Gasoleo A": 0.927518518518519,
            "Precio Gasolina 95 E5": 1.005407407407407,
            "Precio Gasolina 98 E5": 1.0333444444444435,
            "Precio Gasoleo Premium": 0.9589999999999997
        },
        "Melilla": {
            "Precio Gasoleo A": 0.8595000000000004,
            "Precio Gasoleo Premium": 0.9124333333333325,
            "Precio Gasolina 95 E5": 0.9232348484848487
        }
    },
    "Mayo": {
        "País Vasco": {
            "Precio Gasoleo A": 1.1949733138481098,
            "Precio Gasoleo B": 0.9221381558123067,
            "Precio Gasoleo Premium": 1.2633114906680845,
            "Precio Gasolina 95 E5": 1.301255489655384,
            "Precio Gasolina 98 E5": 1.4243604938171994,
            "Precio Biodiesel": 1.1818882795698922,
            "Precio Bioetanol": 1.353887096774193,
            "Precio Gases licuados del petróleo": 0.6643745074467374
        },
        "Castilla la Mancha": {
            "Precio Gasoleo A": 1.220333977430165,
            "Precio Gasoleo B": 0.8627940586582786,
            "Precio Gasolina 95 E5": 1.3285783857150553,
            "Precio Gasoleo Premium": 1.2932054457433866,
            "Precio Gasolina 98 E5": 1.4514533798924647,
            "Precio Gases licuados del petróleo": 0.6782696774193551,
            "Precio Gas Natural Comprimido": 0.9370000000000004,
            "Precio Biodiesel": 1.223387096774193
        },
        "Comunidad Valenciana": {
            "Precio Gasoleo A": 1.2102860368211836,
            "Precio Gasoleo Premium": 1.2858815893669078,
            "Precio Gasolina 95 E5": 1.3252738574196297,
            "Precio Gasolina 98 E5": 1.4542924879997037,
            "Precio Gasoleo B": 0.881009009935321,
            "Precio Gases licuados del petróleo": 0.6754214360041628,
            "Precio Biodiesel": 1.1845529953917047,
            "Precio Gas Natural Comprimido": 0.8590000000000007,
            "Precio Bioetanol": 1.423774193548387
        },
        "Andalucia": {
            "Precio Gasoleo A": 1.2213569290156259,
            "Precio Gasoleo B": 0.8758509565292126,
            "Precio Gasoleo Premium": 1.2932122518947478,
            "Precio Gasolina 95 E5": 1.3381974358189572,
            "Precio Gasolina 98 E5": 1.4622498123973853,
            "Precio Gases licuados del petróleo": 0.6712362371445855,
            "Precio Biodiesel": 1.212591162044897
        },
        "Castilla y León": {
            "Precio Gasoleo A": 1.2013810755408703,
            "Precio Gasoleo Premium": 1.2710051710480867,
            "Precio Gasolina 95 E5": 1.3016860400719414,
            "Precio Gasolina 98 E5": 1.4225095722249685,
            "Precio Gasoleo B": 0.8951217257451693,
            "Precio Gases licuados del petróleo": 0.6680189386056196,
            "Precio Biodiesel": 1.1855325024437926
        },
        "Extremadura": {
            "Precio Gasoleo A": 1.20983155884218,
            "Precio Gasoleo B": 0.8584023097588677,
            "Precio Gasoleo Premium": 1.2821014277175666,
            "Precio Gasolina 95 E5": 1.3213095592090836,
            "Precio Gasolina 98 E5": 1.4473162940664372,
            "Precio Gases licuados del petróleo": 0.6673749999999999,
            "Precio Biodiesel": 1.210661290322581
        },
        "Baleares": {
            "Precio Gasoleo A": 1.2787698999963064,
            "Precio Gasoleo Premium": 1.3394317533200624,
            "Precio Gasolina 95 E5": 1.4101707947751183,
            "Precio Gasolina 98 E5": 1.5299935783911767,
            "Precio Gases licuados del petróleo": 0.6881935483870962,
            "Precio Gasoleo B": 0.9389773432418593
        },
        "Cataluña": {
            "Precio Gasoleo A": 1.2042685148012806,
            "Precio Gasoleo Premium": 1.2852140795183227,
            "Precio Gasolina 95 E5": 1.316651087908744,
            "Precio Gasolina 98 E5": 1.4491959734744428,
            "Precio Gases licuados del petróleo": 0.6415087142660485,
            "Precio Gasoleo B": 0.8813822959222258,
            "Precio Biodiesel": 1.182098428453267,
            "Precio Bioetanol": 1.3820000000000001,
            "Precio Gas Natural Comprimido": 0.8815107526881724
        },
        "Galicia": {
            "Precio Gases licuados del petróleo": 0.6758107526881718,
            "Precio Gasoleo A": 1.2430180586200368,
            "Precio Gasoleo B": 0.9125316619032716,
            "Precio Gasoleo Premium": 1.308963775954618,
            "Precio Gasolina 98 E5": 1.472165389858928,
            "Precio Gasolina 95 E5": 1.3535864218611853,
            "Precio Biodiesel": 1.2088207885304658,
            "Precio Bioetanol": 1.369
        },
        "Aragón": {
            "Precio Gasoleo A": 1.1710326034881777,
            "Precio Gasoleo B": 0.8426009597943361,
            "Precio Gasoleo Premium": 1.2555678677984266,
            "Precio Gasolina 95 E5": 1.2851393688273773,
            "Precio Gasolina 98 E5": 1.413564694092408,
            "Precio Biodiesel": 1.133916218637993,
            "Precio Gases licuados del petróleo": 0.6537172043010753
        },
        "Rioja (La)": {
            "Precio Gasoleo A": 1.1889144259667401,
            "Precio Gasoleo B": 0.8963727598566308,
            "Precio Gasoleo Premium": 1.2645585072738772,
            "Precio Gasolina 95 E5": 1.2963568302184092,
            "Precio Gasolina 98 E5": 1.4162683284457478,
            "Precio Biodiesel": 1.123,
            "Precio Gases licuados del petróleo": 0.6570241935483871
        },
        "Madrid": {
            "Precio Gases licuados del petróleo": 0.6710728580822378,
            "Precio Gasoleo A": 1.2052396630220998,
            "Precio Gasoleo B": 0.9209812241245473,
            "Precio Gasoleo Premium": 1.2685372400846522,
            "Precio Gasolina 95 E5": 1.3097875613871814,
            "Precio Gasolina 98 E5": 1.4314512951666354,
            "Precio Biodiesel": 1.2437500000000001,
            "Precio Bioetanol": 1.3255967741935488
        },
        "Murcia": {
            "Precio Gasoleo A": 1.2066139189682639,
            "Precio Gasoleo B": 0.8868537620747575,
            "Precio Gasolina 95 E5": 1.3213787784063034,
            "Precio Gasolina 98 E5": 1.4431336378231225,
            "Precio Gasoleo Premium": 1.2793475764970956,
            "Precio Gases licuados del petróleo": 0.6521651305683566,
            "Precio Biodiesel": 1.194064516129032
        },
        "Navarra": {
            "Precio Gasoleo A": 1.156249149740333,
            "Precio Gasoleo B": 0.8346362139264483,
            "Precio Gasoleo Premium": 1.24646924325421,
            "Precio Gasolina 95 E5": 1.2774293523153346,
            "Precio Gasolina 98 E5": 1.4049020457253159,
            "Precio Biodiesel": 1.1440189964157705,
            "Precio Gases licuados del petróleo": 0.6596682027649773,
            "Precio Bioetanol": 1.25
        },
        "Asturias": {
            "Precio Gasoleo A": 1.2299324577706927,
            "Precio Gasoleo B": 0.9125955322217141,
            "Precio Gasoleo Premium": 1.296354260058042,
            "Precio Gasolina 95 E5": 1.3458774607996091,
            "Precio Gasolina 98 E5": 1.4667044431033123,
            "Precio Biodiesel": 1.217032258064516,
            "Precio Gases licuados del petróleo": 0.6719589442815247,
            "Precio Bioetanol": 1.459000000000001
        },
        "Canarias": {
            "Precio Gasoleo A": 0.9458148137923252,
            "Precio Gasolina 95 E5": 1.0096375877107404,
            "Precio Gasolina 98 E5": 1.1082576307759693,
            "Precio Gasoleo Premium": 1.0110456827857088,
            "Precio Gases licuados del petróleo": 0.5120660522273428
        },
        "Cantabria": {
            "Precio Gasoleo A": 1.190514358585401,
            "Precio Gasoleo B": 0.8849844030839091,
            "Precio Gasoleo Premium": 1.2602209775331252,
            "Precio Gasolina 95 E5": 1.2990717538148036,
            "Precio Gasolina 98 E5": 1.4164312475129637,
            "Precio Biodiesel": 1.2266290322580646,
            "Precio Gases licuados del petróleo": 0.6602258064516128
        },
        "Ceuta": {
            "Precio Gasoleo A": 0.9300035842293909,
            "Precio Gasolina 95 E5": 1.01800358422939,
            "Precio Gasolina 98 E5": 1.0458924731182793,
            "Precio Gasoleo Premium": 0.959870967741936
        },
        "Melilla": {
            "Precio Gasoleo A": 0.8590806451612911,
            "Precio Gasoleo Premium": 0.911440860215053,
            "Precio Gasolina 95 E5": 0.9328709677419353
        }
    },
    "Junio": {
        "País Vasco": {
            "Precio Gasoleo A": 1.1740341030922903,
            "Precio Gasoleo B": 0.9049062865497074,
            "Precio Gasoleo Premium": 1.2408274278796467,
            "Precio Gasolina 95 E5": 1.315288524500889,
            "Precio Gasolina 98 E5": 1.4391697195214384,
            "Precio Biodiesel": 1.1597479999999998,
            "Precio Bioetanol": 1.3561333333333325,
            "Precio Gases licuados del petróleo": 0.680703914141414
        },
        "Castilla la Mancha": {
            "Precio Gasoleo A": 1.204375044084221,
            "Precio Gasoleo B": 0.8533776232413114,
            "Precio Gasolina 95 E5": 1.3421475065574,
            "Precio Gasoleo Premium": 1.2766698387597855,
            "Precio Gasolina 98 E5": 1.4662475788097318,
            "Precio Gases licuados del petróleo": 0.6929999999999998,
            "Precio Gas Natural Comprimido": 0.9370000000000004,
            "Precio Biodiesel": 1.2035999999999996
        },
        "Comunidad Valenciana": {
            "Precio Gasoleo A": 1.1938158524471845,
            "Precio Gasoleo Premium": 1.2683307664168628,
            "Precio Gasolina 95 E5": 1.3397206793962135,
            "Precio Gasolina 98 E5": 1.47023093328627,
            "Precio Gasoleo B": 0.8739268450831782,
            "Precio Gases licuados del petróleo": 0.6927795454545455,
            "Precio Biodiesel": 1.1757166666666667,
            "Precio Gas Natural Comprimido": 0.9409999999999997,
            "Precio Bioetanol": 1.3950333333333333
        },
        "Andalucia": {
            "Precio Gasoleo A": 1.203604236448402,
            "Precio Gasoleo B": 0.866625418356324,
            "Precio Gasoleo Premium": 1.2751636557793522,
            "Precio Gasolina 95 E5": 1.3521343940946084,
            "Precio Gasolina 98 E5": 1.4773584904475474,
            "Precio Gases licuados del petróleo": 0.6860951495483304,
            "Precio Biodiesel": 1.2007726120857696
        },
        "Castilla y León": {
            "Precio Gasoleo A": 1.1820633135884584,
            "Precio Gasoleo Premium": 1.251731624549419,
            "Precio Gasolina 95 E5": 1.3149979418549214,
            "Precio Gasolina 98 E5": 1.4374198939730725,
            "Precio Gasoleo B": 0.8853754830537931,
            "Precio Gases licuados del petróleo": 0.6825721774193547,
            "Precio Biodiesel": 1.1765305555555554
        },
        "Extremadura": {
            "Precio Gasoleo A": 1.1936451562326118,
            "Precio Gasoleo B": 0.8512395084406715,
            "Precio Gasoleo Premium": 1.2656232586374436,
            "Precio Gasolina 95 E5": 1.3338223869244812,
            "Precio Gasolina 98 E5": 1.4604429139147295,
            "Precio Gases licuados del petróleo": 0.6850345238095237,
            "Precio Biodiesel": 1.1932333333333334
        },
        "Baleares": {
            "Precio Gasoleo A": 1.259057495802613,
            "Precio Gasoleo Premium": 1.3214740830334801,
            "Precio Gasolina 95 E5": 1.4164634816831525,
            "Precio Gasolina 98 E5": 1.5366170654920706,
            "Precio Gases licuados del petróleo": 0.6962615384615387,
            "Precio Gasoleo B": 0.9221915915915918
        },
        "Cataluña": {
            "Precio Gasoleo A": 1.187429446036473,
            "Precio Gasoleo Premium": 1.268358741180304,
            "Precio Gasolina 95 E5": 1.3299768566894485,
            "Precio Gasolina 98 E5": 1.4646821783669361,
            "Precio Gases licuados del petróleo": 0.6531075494809431,
            "Precio Gasoleo B": 0.8694460851575777,
            "Precio Biodiesel": 1.1714357535210165,
            "Precio Bioetanol": 1.4090666666666671,
            "Precio Gas Natural Comprimido": 0.889283333333333
        },
        "Galicia": {
            "Precio Gases licuados del petróleo": 0.6923502564102564,
            "Precio Gasoleo A": 1.2228013125997446,
            "Precio Gasoleo B": 0.9010054294783578,
            "Precio Gasoleo Premium": 1.289694670705832,
            "Precio Gasolina 98 E5": 1.4875950250628944,
            "Precio Gasolina 95 E5": 1.3673774540278305,
            "Precio Biodiesel": 1.1964296296296302,
            "Precio Bioetanol": 1.4015333333333329
        },
        "Aragón": {
            "Precio Gasoleo A": 1.1542297616057486,
            "Precio Gasoleo B": 0.8328629933061962,
            "Precio Gasoleo Premium": 1.237035774231153,
            "Precio Gasolina 95 E5": 1.2988458591111616,
            "Precio Gasolina 98 E5": 1.4290978789113842,
            "Precio Biodiesel": 1.1218037037037039,
            "Precio Gases licuados del petróleo": 0.667952331002331
        },
        "Rioja (La)": {
            "Precio Gasoleo A": 1.1729454470300058,
            "Precio Gasoleo B": 0.8831476054809386,
            "Precio Gasoleo Premium": 1.2475506535947711,
            "Precio Gasolina 95 E5": 1.308833837844028,
            "Precio Gasolina 98 E5": 1.4316878787878786,
            "Precio Biodiesel": 1.1085,
            "Precio Gases licuados del petróleo": 0.6707500000000002
        },
        "Madrid": {
            "Precio Gases licuados del petróleo": 0.6870703023267273,
            "Precio Gasoleo A": 1.1874080388777803,
            "Precio Gasoleo B": 0.9056917450716843,
            "Precio Gasoleo Premium": 1.2506373723035116,
            "Precio Gasolina 95 E5": 1.3224997161968832,
            "Precio Gasolina 98 E5": 1.446281185122974,
            "Precio Biodiesel": 1.2245083333333333,
            "Precio Bioetanol": 1.3777999999999995
        },
        "Murcia": {
            "Precio Gasoleo A": 1.1908109011798236,
            "Precio Gasoleo B": 0.8777349728221481,
            "Precio Gasolina 95 E5": 1.3373933211846727,
            "Precio Gasolina 98 E5": 1.4620883008209327,
            "Precio Gasoleo Premium": 1.263292119693535,
            "Precio Gases licuados del petróleo": 0.666798412698413,
            "Precio Biodiesel": 1.1786666666666659
        },
        "Navarra": {
            "Precio Gasoleo A": 1.1406095450542248,
            "Precio Gasoleo B": 0.8236136348454668,
            "Precio Gasoleo Premium": 1.2290233710031295,
            "Precio Gasolina 95 E5": 1.2886609181205912,
            "Precio Gasolina 98 E5": 1.4192573952126597,
            "Precio Biodiesel": 1.13217037037037,
            "Precio Gases licuados del petróleo": 0.6717269841269842
        },
        "Asturias": {
            "Precio Gasoleo A": 1.2107837707016116,
            "Precio Gasoleo B": 0.9007958016348248,
            "Precio Gasoleo Premium": 1.2781479023531832,
            "Precio Gasolina 95 E5": 1.3590100908740406,
            "Precio Gasolina 98 E5": 1.4799574746058808,
            "Precio Biodiesel": 1.2001833333333338,
            "Precio Gases licuados del petróleo": 0.6909585858585859,
            "Precio Bioetanol": 1.4803333333333337
        },
        "Canarias": {
            "Precio Gasoleo A": 0.9468157675766029,
            "Precio Gasolina 95 E5": 1.0268579757530973,
            "Precio Gasolina 98 E5": 1.1279881751797578,
            "Precio Gasoleo Premium": 1.0121122801625828,
            "Precio Gases licuados del petróleo": 0.5012087301587305
        },
        "Cantabria": {
            "Precio Gasoleo A": 1.1743714252094712,
            "Precio Gasoleo B": 0.884702192285761,
            "Precio Gasoleo Premium": 1.2437639421845605,
            "Precio Gasolina 95 E5": 1.3144318532854118,
            "Precio Gasolina 98 E5": 1.4322538984186004,
            "Precio Biodiesel": 1.216714444444445,
            "Precio Gases licuados del petróleo": 0.6765833333333331
        },
        "Ceuta": {
            "Precio Gasoleo A": 0.9404074074074078,
            "Precio Gasolina 95 E5": 1.0284074074074065,
            "Precio Gasolina 98 E5": 1.056370370370371,
            "Precio Gasoleo Premium": 0.973866666666667
        },
        "Melilla": {
            "Precio Gasoleo A": 0.8607499999999997,
            "Precio Gasoleo Premium": 0.9136666666666663,
            "Precio Gasolina 95 E5": 0.9409090909090911
        }
    },
    "Julio": {
        "País Vasco": {
            "Precio Gasoleo A": 1.1391957463843183,
            "Precio Gasoleo B": 0.8735687607949493,
            "Precio Gasoleo Premium": 1.2062755772567126,
            "Precio Gasolina 95 E5": 1.3012983256113795,
            "Precio Gasolina 98 E5": 1.4234211991734378,
            "Precio Biodiesel": 1.1294488709677422,
            "Precio Bioetanol": 1.3525118279569888,
            "Precio Gases licuados del petróleo": 0.6613523726040206
        },
        "Castilla la Mancha": {
            "Precio Gasoleo A": 1.1654034058565914,
            "Precio Gasoleo B": 0.8282928575287256,
            "Precio Gasolina 95 E5": 1.3246290163515366,
            "Precio Gasoleo Premium": 1.2378605208483073,
            "Precio Gasolina 98 E5": 1.4476853436208115,
            "Precio Gases licuados del petróleo": 0.6736088172043008,
            "Precio Gas Natural Comprimido": 0.9370000000000004,
            "Precio Biodiesel": 1.1545806451612903
        },
        "Comunidad Valenciana": {
            "Precio Gasoleo A": 1.1614076752603435,
            "Precio Gasoleo Premium": 1.2370232919074384,
            "Precio Gasolina 95 E5": 1.3332143548098672,
            "Precio Gasolina 98 E5": 1.4642535635349092,
            "Precio Gasoleo B": 0.8519431352393552,
            "Precio Gases licuados del petróleo": 0.6725070564516133,
            "Precio Biodiesel": 1.1443099078341015,
            "Precio Gas Natural Comprimido": 0.9409999999999997,
            "Precio Bioetanol": 1.344548387096774
        },
        "Andalucia": {
            "Precio Gasoleo A": 1.1697304365398367,
            "Precio Gasoleo B": 0.842003701789261,
            "Precio Gasoleo Premium": 1.2416521820267705,
            "Precio Gasolina 95 E5": 1.3419555943136483,
            "Precio Gasolina 98 E5": 1.466919643702135,
            "Precio Gases licuados del petróleo": 0.6674471454500063,
            "Precio Biodiesel": 1.171723371283998
        },
        "Castilla y León": {
            "Precio Gasoleo A": 1.142419481944736,
            "Precio Gasoleo Premium": 1.2120367544866792,
            "Precio Gasolina 95 E5": 1.29690977467242,
            "Precio Gasolina 98 E5": 1.4188489269176783,
            "Precio Gasoleo B": 0.8590191596747601,
            "Precio Gases licuados del petróleo": 0.6675846774193547,
            "Precio Biodiesel": 1.1408333333333336
        },
        "Extremadura": {
            "Precio Gasoleo A": 1.1586426993153522,
            "Precio Gasoleo B": 0.8309764433518606,
            "Precio Gasoleo Premium": 1.2313042905736535,
            "Precio Gasolina 95 E5": 1.3187946991846302,
            "Precio Gasolina 98 E5": 1.4456647574867454,
            "Precio Gases licuados del petróleo": 0.6668940092165896,
            "Precio Biodiesel": 1.14991935483871
        },
        "Baleares": {
            "Precio Gasoleo A": 1.2196608983481882,
            "Precio Gasoleo Premium": 1.2857825656662922,
            "Precio Gasolina 95 E5": 1.4006168696889854,
            "Precio Gasolina 98 E5": 1.525465195198284,
            "Precio Gases licuados del petróleo": 0.6775607940446653,
            "Precio Gasoleo B": 0.8924263295553622
        },
        "Cataluña": {
            "Precio Gasoleo A": 1.1524180926894079,
            "Precio Gasoleo Premium": 1.2350272224440848,
            "Precio Gasolina 95 E5": 1.3213336792199413,
            "Precio Gasolina 98 E5": 1.4558144213955526,
            "Precio Gases licuados del petróleo": 0.6278409330881802,
            "Precio Gasoleo B": 0.8437663581366621,
            "Precio Biodiesel": 1.1400552203897203,
            "Precio Bioetanol": 1.4623387096774187,
            "Precio Gas Natural Comprimido": 0.8897499999999996
        },
        "Galicia": {
            "Precio Gases licuados del petróleo": 0.6794876261373033,
            "Precio Gasoleo A": 1.186477726499757,
            "Precio Gasoleo B": 0.8751037477839774,
            "Precio Gasoleo Premium": 1.2544730221690925,
            "Precio Gasolina 98 E5": 1.4768453292834756,
            "Precio Gasolina 95 E5": 1.3561549182698227,
            "Precio Biodiesel": 1.1706594982078848,
            "Precio Bioetanol": 1.40348275862069
        },
        "Aragón": {
            "Precio Gasoleo A": 1.1157829795690473,
            "Precio Gasoleo B": 0.8031984483761434,
            "Precio Gasoleo Premium": 1.1970522184131107,
            "Precio Gasolina 95 E5": 1.2814547536383087,
            "Precio Gasolina 98 E5": 1.4092326673188265,
            "Precio Biodiesel": 1.090859318996416,
            "Precio Gases licuados del petróleo": 0.6496757086999025
        },
        "Rioja (La)": {
            "Precio Gasoleo A": 1.1297399844446137,
            "Precio Gasoleo B": 0.8476737012091852,
            "Precio Gasoleo Premium": 1.2060978254527612,
            "Precio Gasolina 95 E5": 1.289288587261098,
            "Precio Gasolina 98 E5": 1.409142774329946,
            "Precio Biodiesel": 1.0667741935483872,
            "Precio Gases licuados del petróleo": 0.6554112903225802
        },
        "Madrid": {
            "Precio Gases licuados del petróleo": 0.6689729621368106,
            "Precio Gasoleo A": 1.1516479432549134,
            "Precio Gasoleo B": 0.8759937275212798,
            "Precio Gasoleo Premium": 1.2150282868357973,
            "Precio Gasolina 95 E5": 1.310015663429201,
            "Precio Gasolina 98 E5": 1.4344664825925924,
            "Precio Biodiesel": 1.192637096774193,
            "Precio Bioetanol": 1.3866612903225812
        },
        "Murcia": {
            "Precio Gasoleo A": 1.158004276435029,
            "Precio Gasoleo B": 0.8538163091862842,
            "Precio Gasoleo Premium": 1.2316562582375423,
            "Precio Gasolina 95 E5": 1.3331594161705587,
            "Precio Gasolina 98 E5": 1.4579361493153666,
            "Precio Gases licuados del petróleo": 0.6498686635944704,
            "Precio Biodiesel": 1.1714193548387097
        },
        "Navarra": {
            "Precio Gasoleo A": 1.104884878645615,
            "Precio Gasoleo B": 0.7962036762846059,
            "Precio Gasoleo Premium": 1.1928966677506818,
            "Precio Gasolina 95 E5": 1.282370035511705,
            "Precio Gasolina 98 E5": 1.4078765269240907,
            "Precio Biodiesel": 1.103714157706093,
            "Precio Gases licuados del petróleo": 0.6602089093701994
        },
        "Asturias": {
            "Precio Gasoleo A": 1.1753677448161772,
            "Precio Gasoleo B": 0.8723638690012846,
            "Precio Gasoleo Premium": 1.2424437735618363,
            "Precio Gasolina 95 E5": 1.3461680235173688,
            "Precio Gasolina 98 E5": 1.4669810637029572,
            "Precio Gases licuados del petróleo": 0.6773548387096776,
            "Precio Biodiesel": 1.1698548387096777,
            "Precio Bioetanol": 1.4860967741935482
        },
        "Canarias": {
            "Precio Gasoleo A": 0.9341174993412781,
            "Precio Gasolina 95 E5": 1.0312308684539753,
            "Precio Gasolina 98 E5": 1.1304269659941264,
            "Precio Gasoleo Premium": 0.9985360149989687,
            "Precio Gases licuados del petróleo": 0.49107661290322585
        },
        "Cantabria": {
            "Precio Gasoleo A": 1.1417479291915817,
            "Precio Gasoleo B": 0.8691793820751745,
            "Precio Gasoleo Premium": 1.2091174408860537,
            "Precio Gasolina 95 E5": 1.3040696457555332,
            "Precio Gasolina 98 E5": 1.4226250800038907,
            "Precio Biodiesel": 1.1967838709677425,
            "Precio Gases licuados del petróleo": 0.6664528347996092
        },
        "Ceuta": {
            "Precio Gasoleo A": 0.946498207885305,
            "Precio Gasolina 95 E5": 1.0341111111111108,
            "Precio Gasolina 98 E5": 1.061229390681004,
            "Precio Gasoleo Premium": 0.9800000000000003
        },
        "Melilla": {
            "Precio Gasoleo A": 0.8589019851116625,
            "Precio Gasoleo Premium": 0.9094204301075272,
            "Precio Gasolina 95 E5": 0.9436891495601174
        }
    },
    "Agosto": {
        "País Vasco": {
            "Precio Gasoleo A": 1.0797876556550359,
            "Precio Gasoleo B": 0.8191033228231867,
            "Precio Gasoleo Premium": 1.14895409819436,
            "Precio Gasolina 95 E5": 1.21806983471255,
            "Precio Gasolina 98 E5": 1.3388539091957499,
            "Precio Biodiesel": 1.0766638709677423,
            "Precio Bioetanol": 1.3469698924731186,
            "Precio Gases licuados del petróleo": 0.6274109957924261
        },
        "Castilla la Mancha": {
            "Precio Gasoleo A": 1.1019798385219652,
            "Precio Gasoleo B": 0.7757615701904464,
            "Precio Gasolina 95 E5": 1.2484091211417099,
            "Precio Gasoleo Premium": 1.1757493700310406,
            "Precio Gasolina 98 E5": 1.3725661887368446,
            "Precio Gases licuados del petróleo": 0.6411264516129032,
            "Precio Gas Natural Comprimido": 0.9370000000000004,
            "Precio Biodiesel": 1.0971612903225805
        },
        "Comunidad Valenciana": {
            "Precio Gasoleo A": 1.101782243483702,
            "Precio Gasoleo Premium": 1.1790151294916287,
            "Precio Gasolina 95 E5": 1.257213608815419,
            "Precio Gasolina 98 E5": 1.3895502500213388,
            "Precio Gasoleo B": 0.8017655696462448,
            "Precio Gases licuados del petróleo": 0.6418640029325512,
            "Precio Biodiesel": 1.0990760368663597,
            "Precio Gas Natural Comprimido": 0.9409999999999997,
            "Precio Bioetanol": 1.2801935483870965
        },
        "Andalucia": {
            "Precio Gasoleo A": 1.1103654379415941,
            "Precio Gasoleo B": 0.7892571614680702,
            "Precio Gasoleo Premium": 1.1821619207573923,
            "Precio Gasolina 95 E5": 1.2641649749184771,
            "Precio Gasolina 98 E5": 1.3902493583637212,
            "Precio Gases licuados del petróleo": 0.6404830430630541,
            "Precio Biodiesel": 1.106442703533026
        },
        "Castilla y León": {
            "Precio Gasoleo A": 1.0765939376952558,
            "Precio Gasoleo B": 0.8049130768858813,
            "Precio Gasoleo Premium": 1.1482679733801955,
            "Precio Gasolina 95 E5": 1.2180804383063975,
            "Precio Gasolina 98 E5": 1.3412991058964743,
            "Precio Gases licuados del petróleo": 0.6355181451612905,
            "Precio Biodiesel": 1.0797600195503418
        },
        "Extremadura": {
            "Precio Gasoleo A": 1.0940382155482011,
            "Precio Gasoleo B": 0.7877069420905367,
            "Precio Gasoleo Premium": 1.1670260788839237,
            "Precio Gasolina 95 E5": 1.2411908259767068,
            "Precio Gasolina 98 E5": 1.3731432598280142,
            "Precio Gases licuados del petróleo": 0.634332949308756,
            "Precio Biodiesel": 1.067806451612903
        },
        "Baleares": {
            "Precio Gasoleo A": 1.1573110539847433,
            "Precio Gasoleo Premium": 1.2248121015730955,
            "Precio Gasolina 95 E5": 1.3148100816486614,
            "Precio Gasolina 98 E5": 1.4406908684366555,
            "Precio Gases licuados del petróleo": 0.6577468982630271,
            "Precio Gasoleo B": 0.832524798992541
        },
        "Cataluña": {
            "Precio Gasoleo A": 1.0952361662024204,
            "Precio Gasoleo Premium": 1.1783411185631334,
            "Precio Gasolina 95 E5": 1.2474744698348692,
            "Precio Gasolina 98 E5": 1.3810690432375612,
            "Precio Gases licuados del petróleo": 0.6058260382796711,
            "Precio Gasoleo B": 0.7928433322774778,
            "Precio Biodiesel": 1.0906345773842339,
            "Precio Bioetanol": 1.3744838709677416,
            "Precio Gas Natural Comprimido": 0.8895241935483863
        },
        "Galicia": {
            "Precio Gases licuados del petróleo": 0.653298685782557,
            "Precio Gasoleo A": 1.1250052871819878,
            "Precio Gasoleo B": 0.8198968870109569,
            "Precio Gasoleo Premium": 1.1919605296925742,
            "Precio Gasolina 98 E5": 1.400986566927108,
            "Precio Gasolina 95 E5": 1.2773461390439769,
            "Precio Biodiesel": 1.1168848566308243,
            "Precio Bioetanol": 1.361870967741935
        },
        "Aragón": {
            "Precio Gasoleo A": 1.0533863257124627,
            "Precio Gasoleo B": 0.7487918732582008,
            "Precio Gasoleo Premium": 1.133800068778352,
            "Precio Gasolina 95 E5": 1.2004484031129532,
            "Precio Gasolina 98 E5": 1.3272466290367595,
            "Precio Biodiesel": 1.0470432027649772,
            "Precio Gases licuados del petróleo": 0.6180521279795473
        },
        "Rioja (La)": {
            "Precio Gasoleo A": 1.0674182010114397,
            "Precio Gasoleo B": 0.7964067673664447,
            "Precio Gasoleo Premium": 1.1461499051233397,
            "Precio Gasolina 95 E5": 1.2133847325185336,
            "Precio Gasolina 98 E5": 1.3323217281593127,
            "Precio Biodiesel": 1.0041935483870967,
            "Precio Gases licuados del petróleo": 0.6245725806451616
        },
        "Madrid": {
            "Precio Gases licuados del petróleo": 0.6327804570448631,
            "Precio Gasoleo A": 1.091632335832957,
            "Precio Gasoleo B": 0.8201529943533082,
            "Precio Gasoleo Premium": 1.1554295764410978,
            "Precio Gasolina 95 E5": 1.2321080605191808,
            "Precio Gasolina 98 E5": 1.3581040961839292,
            "Precio Biodiesel": 1.1323629032258062,
            "Precio Bioetanol": 1.2966612903225803
        },
        "Murcia": {
            "Precio Gasoleo A": 1.0975115550120647,
            "Precio Gasoleo B": 0.8027243172883556,
            "Precio Gasoleo Premium": 1.171123418260975,
            "Precio Gasolina 95 E5": 1.2539742362900608,
            "Precio Gasolina 98 E5": 1.3806316307843276,
            "Precio Gases licuados del petróleo": 0.6254437788018434,
            "Precio Biodiesel": 1.0974623655913975
        },
        "Navarra": {
            "Precio Gasoleo A": 1.0439923460101417,
            "Precio Gasoleo B": 0.7446128003550201,
            "Precio Gasoleo Premium": 1.1333855075032497,
            "Precio Gasolina 95 E5": 1.2127237998601512,
            "Precio Gasolina 98 E5": 1.3360340112201965,
            "Precio Biodiesel": 1.0282159498207886,
            "Precio Gases licuados del petróleo": 0.6319354838709678
        },
        "Asturias": {
            "Precio Gasoleo A": 1.114267070008357,
            "Precio Gasoleo B": 0.8144253409544828,
            "Precio Gasoleo Premium": 1.1829871886294694,
            "Precio Gasolina 95 E5": 1.2677535077120954,
            "Precio Gasolina 98 E5": 1.3866740754850302,
            "Precio Gases licuados del petróleo": 0.6487553763440856,
            "Precio Biodiesel": 1.110822580645161,
            "Precio Bioetanol": 1.4135161290322582
        },
        "Canarias": {
            "Precio Gasoleo A": 0.89785712044041,
            "Precio Gasolina 95 E5": 1.0057762432083053,
            "Precio Gasolina 98 E5": 1.1025303224364342,
            "Precio Gasoleo Premium": 0.962193396321285,
            "Precio Gases licuados del petróleo": 0.4874516129032259
        },
        "Cantabria": {
            "Precio Gasoleo A": 1.079100191189098,
            "Precio Gasoleo B": 0.8299259905243904,
            "Precio Gasoleo Premium": 1.1475326010450084,
            "Precio Gasolina 95 E5": 1.2270297659391756,
            "Precio Gasolina 98 E5": 1.3505478709850174,
            "Precio Biodiesel": 1.1387999999999996,
            "Precio Gases licuados del petróleo": 0.6415887096774193
        },
        "Ceuta": {
            "Precio Gasoleo A": 0.9439354838709678,
            "Precio Gasolina 95 E5": 1.0321218637992835,
            "Precio Gasolina 98 E5": 1.0601935483870977,
            "Precio Gasoleo Premium": 0.9766387096774193
        },
        "Melilla": {
            "Precio Gasoleo A": 0.8446501240694787,
            "Precio Gasoleo Premium": 0.8954258064516126,
            "Precio Gasolina 95 E5": 0.94007917888563
        }
    },
    "Septiembre": {
        "País Vasco": {
            "Precio Gasoleo A": 1.0714986086538552,
            "Precio Gasoleo B": 0.8094263157894735,
            "Precio Gasoleo Premium": 1.1406652582159622,
            "Precio Gasolina 95 E5": 1.1653137041067652,
            "Precio Gasolina 98 E5": 1.2881773415949893,
            "Precio Biodiesel": 1.0672733333333335,
            "Precio Bioetanol": 1.3341555555555553,
            "Precio Gases licuados del petróleo": 0.5887191304347825
        },
        "Castilla la Mancha": {
            "Precio Gasoleo A": 1.0944998476703927,
            "Precio Gasoleo B": 0.7539501916974848,
            "Precio Gasolina 95 E5": 1.195866593451803,
            "Precio Gasoleo Premium": 1.1714455372560435,
            "Precio Gasolina 98 E5": 1.3250164651266159,
            "Precio Gases licuados del petróleo": 0.5988986666666666,
            "Precio Gas Natural Comprimido": 0.9370000000000004,
            "Precio Biodiesel": 1.0049999999999994
        },
        "Comunidad Valenciana": {
            "Precio Gasoleo A": 1.0842695657632249,
            "Precio Gasoleo Premium": 1.1625576156749733,
            "Precio Gasolina 95 E5": 1.1992220456537213,
            "Precio Gasolina 98 E5": 1.333261113656471,
            "Precio Gasoleo B": 0.77906484820965,
            "Precio Gases licuados del petróleo": 0.6035720439691029,
            "Precio Biodiesel": 1.0608749999999998,
            "Precio Gas Natural Comprimido": 0.9409999999999997,
            "Precio Bioetanol": 1.2287666666666672
        },
        "Andalucia": {
            "Precio Gasoleo A": 1.0965929795729907,
            "Precio Gasoleo B": 0.7690345257832379,
            "Precio Gasoleo Premium": 1.1707681352602535,
            "Precio Gasolina 95 E5": 1.2090966184233014,
            "Precio Gasolina 98 E5": 1.3377860492824714,
            "Precio Gases licuados del petróleo": 0.6062418819322308,
            "Precio Biodiesel": 1.0820877289377289
        },
        "Castilla y León": {
            "Precio Gasoleo A": 1.0736750393487084,
            "Precio Gasoleo B": 0.7874703534898592,
            "Precio Gasoleo Premium": 1.145700126098221,
            "Precio Gasolina 95 E5": 1.1658102851288854,
            "Precio Gasolina 98 E5": 1.290868854953658,
            "Precio Gases licuados del petróleo": 0.593166666666667,
            "Precio Biodiesel": 1.0768055555555556
        },
        "Extremadura": {
            "Precio Gasoleo A": 1.0845197971267442,
            "Precio Gasoleo B": 0.7698678585270249,
            "Precio Gasoleo Premium": 1.159576305817482,
            "Precio Gasolina 95 E5": 1.1902065368935466,
            "Precio Gasolina 98 E5": 1.3261617661891012,
            "Precio Gases licuados del petróleo": 0.5907500000000001,
            "Precio Biodiesel": 1.0704666666666662
        },
        "Baleares": {
            "Precio Gasoleo A": 1.145071096017786,
            "Precio Gasoleo Premium": 1.2113839560639066,
            "Precio Gasolina 95 E5": 1.2601299431507187,
            "Precio Gasolina 98 E5": 1.3844722536371665,
            "Precio Gases licuados del petróleo": 0.618,
            "Precio Gasoleo B": 0.8205459459459459
        },
        "Cataluña": {
            "Precio Gasoleo A": 1.0779512270543408,
            "Precio Gasoleo Premium": 1.1631997436044552,
            "Precio Gasolina 95 E5": 1.1900210053387983,
            "Precio Gasolina 98 E5": 1.3274366145366099,
            "Precio Gases licuados del petróleo": 0.5729821151742465,
            "Precio Gasoleo B": 0.7719439332868323,
            "Precio Biodiesel": 1.0677406352737604,
            "Precio Bioetanol": 1.3401666666666658,
            "Precio Gas Natural Comprimido": 0.8803000000000003
        },
        "Galicia": {
            "Precio Gases licuados del petróleo": 0.6162691358024694,
            "Precio Gasoleo A": 1.1175767315116532,
            "Precio Gasoleo B": 0.8027325982322941,
            "Precio Gasoleo Premium": 1.1841701797056683,
            "Precio Gasolina 98 E5": 1.3466881377587732,
            "Precio Gasolina 95 E5": 1.2212362008738182,
            "Precio Biodiesel": 1.0964425925925922,
            "Precio Bioetanol": 1.3046666666666662
        },
        "Aragón": {
            "Precio Gasoleo A": 1.044608425176391,
            "Precio Gasoleo B": 0.727900850134958,
            "Precio Gasoleo Premium": 1.128831531127885,
            "Precio Gasolina 95 E5": 1.148912473169482,
            "Precio Gasolina 98 E5": 1.279903606512138,
            "Precio Biodiesel": 1.0321624999999999,
            "Precio Gases licuados del petróleo": 0.5729545454545453
        },
        "Rioja (La)": {
            "Precio Gasoleo A": 1.0620648500118726,
            "Precio Gasoleo B": 0.7828054395604395,
            "Precio Gasoleo Premium": 1.1388258280542987,
            "Precio Gasolina 95 E5": 1.160768961038961,
            "Precio Gasolina 98 E5": 1.2854174947145873,
            "Precio Biodiesel": 1.0007833333333338,
            "Precio Gases licuados del petróleo": 0.5784999999999999
        },
        "Madrid": {
            "Precio Gases licuados del petróleo": 0.588946114725378,
            "Precio Gasoleo A": 1.0802910763766134,
            "Precio Gasoleo B": 0.7955682412358882,
            "Precio Gasoleo Premium": 1.1445467450406115,
            "Precio Gasolina 95 E5": 1.1783309904166877,
            "Precio Gasolina 98 E5": 1.3036590161890502,
            "Precio Biodiesel": 1.123591666666667,
            "Precio Bioetanol": 1.2337833333333337
        },
        "Murcia": {
            "Precio Gasoleo A": 1.0827922871039715,
            "Precio Gasoleo B": 0.7808539047095303,
            "Precio Gasolina 95 E5": 1.198481900316733,
            "Precio Gasolina 98 E5": 1.326897147059114,
            "Precio Gasoleo Premium": 1.1575709418762015,
            "Precio Gases licuados del petróleo": 0.5913095238095238,
            "Precio Biodiesel": 1.0829444444444436
        },
        "Navarra": {
            "Precio Gasoleo A": 1.0326357394941141,
            "Precio Gasoleo B": 0.7250373201276481,
            "Precio Gasoleo Premium": 1.1235609596713965,
            "Precio Gasolina 95 E5": 1.1498871028207305,
            "Precio Gasolina 98 E5": 1.2802739210065297,
            "Precio Biodiesel": 0.9962740740740742,
            "Precio Gases licuados del petróleo": 0.5976738095238096
        },
        "Asturias": {
            "Precio Gasoleo A": 1.1042770868162681,
            "Precio Gasoleo B": 0.7959375839188133,
            "Precio Gasoleo Premium": 1.174867098643438,
            "Precio Gasolina 95 E5": 1.2156272419613359,
            "Precio Gasolina 98 E5": 1.3349588453313979,
            "Precio Gases licuados del petróleo": 0.613,
            "Precio Biodiesel": 1.0886666666666671,
            "Precio Bioetanol": 1.3980000000000008
        },
        "Canarias": {
            "Precio Gasoleo A": 0.8559751430302786,
            "Precio Gasolina 95 E5": 0.9480101372418851,
            "Precio Gasolina 98 E5": 1.042846985628547,
            "Precio Gasoleo Premium": 0.9216789981991399,
            "Precio Gases licuados del petróleo": 0.4676595238095239,
            "Precio Gasoleo B": 0.886
        },
        "Cantabria": {
            "Precio Gasoleo A": 1.0641685291256662,
            "Precio Gasoleo B": 0.8062024590664714,
            "Precio Gasoleo Premium": 1.1330066328966601,
            "Precio Gasolina 95 E5": 1.1654080671399822,
            "Precio Gasolina 98 E5": 1.2903859971480005,
            "Precio Biodiesel": 1.0800600000000002,
            "Precio Gases licuados del petróleo": 0.6075861111111113
        },
        "Ceuta": {
            "Precio Gasoleo A": 0.9014518518518514,
            "Precio Gasolina 95 E5": 0.9821296296296299,
            "Precio Gasolina 98 E5": 1.0117777777777774,
            "Precio Gasoleo Premium": 0.933733333333334
        },
        "Melilla": {
            "Precio Gasoleo A": 0.8060358974358978,
            "Precio Gasoleo Premium": 0.856484444444444,
            "Precio Gasolina 95 E5": 0.896948484848485
        }
    },
    "Octubre": {
        "País Vasco": {
            "Precio Gasoleo A": 1.0577379644032348,
            "Precio Gasoleo B": 0.7961584704252286,
            "Precio Gasoleo Premium": 1.1259735045746435,
            "Precio Gasolina 95 E5": 1.1456772381279388,
            "Precio Gasolina 98 E5": 1.2693849316288512,
            "Precio Biodiesel": 1.0562480762038333,
            "Precio Bioetanol": 1.3314193548387105,
            "Precio Gases licuados del petróleo": 0.5916389340813464
        },
        "Castilla la Mancha": {
            "Precio Gasoleo A": 1.0838544035700008,
            "Precio Gasoleo B": 0.7401699165280587,
            "Precio Gasolina 95 E5": 1.1803585177271143,
            "Precio Gasoleo Premium": 1.1602403936889403,
            "Precio Gasolina 98 E5": 1.3094391812620685,
            "Precio Gases licuados del petróleo": 0.6037651612903225,
            "Precio Gas Natural Comprimido": 0.9370000000000004,
            "Precio Biodiesel": 0.9989999999999996
        },
        "Comunidad Valenciana": {
            "Precio Gasoleo A": 1.0690446429982428,
            "Precio Gasoleo Premium": 1.1456139009925663,
            "Precio Gasolina 95 E5": 1.175929662075542,
            "Precio Gasolina 98 E5": 1.3102550481204003,
            "Precio Gasoleo B": 0.7647184301586231,
            "Precio Gases licuados del petróleo": 0.6033124423963132,
            "Precio Biodiesel": 1.0332304147465436,
            "Precio Gas Natural Comprimido": 0.9116451612903222,
            "Precio Bioetanol": 1.2023548387096772
        },
        "Andalucia": {
            "Precio Gasoleo A": 1.0806681439873316,
            "Precio Gasoleo B": 0.7564461351774195,
            "Precio Gasoleo Premium": 1.1547466911646675,
            "Precio Gasolina 95 E5": 1.1874909814109984,
            "Precio Gasolina 98 E5": 1.3154879318316564,
            "Precio Gases licuados del petróleo": 0.6082467044990358,
            "Precio Biodiesel": 1.0606162708259483
        },
        "Castilla y León": {
            "Precio Gasoleo A": 1.0636099943418966,
            "Precio Gasoleo B": 0.7742271412962389,
            "Precio Gasoleo Premium": 1.1345645217897173,
            "Precio Gasolina 95 E5": 1.150486723785638,
            "Precio Gasolina 98 E5": 1.2753034305449082,
            "Precio Gases licuados del petróleo": 0.5965049536073537,
            "Precio Biodiesel": 1.0712776148582601
        },
        "Extremadura": {
            "Precio Gasoleo A": 1.0733939815620541,
            "Precio Gasoleo B": 0.7514085932791974,
            "Precio Gasoleo Premium": 1.1477903273989336,
            "Precio Gasolina 95 E5": 1.173934365028253,
            "Precio Gasolina 98 E5": 1.3098721270032716,
            "Precio Gases licuados del petróleo": 0.5974354838709676,
            "Precio Biodiesel": 1.0602741935483873
        },
        "Baleares": {
            "Precio Gasoleo A": 1.1272838328906618,
            "Precio Gasoleo Premium": 1.1934984434773215,
            "Precio Gasolina 95 E5": 1.2259212571431832,
            "Precio Gasolina 98 E5": 1.3535103141497726,
            "Precio Gases licuados del petróleo": 0.6256526054590573,
            "Precio Gasoleo B": 0.8064088927637316
        },
        "Cataluña": {
            "Precio Gasoleo A": 1.0635905921766198,
            "Precio Gasoleo Premium": 1.146619780538179,
            "Precio Gasolina 95 E5": 1.168249592046997,
            "Precio Gasolina 98 E5": 1.3057369133357382,
            "Precio Gases licuados del petróleo": 0.5766614453152039,
            "Precio Gasoleo B": 0.7563648440240593,
            "Precio Biodiesel": 1.0532273493846205,
            "Precio Bioetanol": 1.3351290322580653,
            "Precio Gas Natural Comprimido": 0.8722500000000003
        },
        "Galicia": {
            "Precio Gases licuados del petróleo": 0.6166116165793584,
            "Precio Gasoleo A": 1.1043117261568884,
            "Precio Gasoleo B": 0.7914668787218189,
            "Precio Gasoleo Premium": 1.1722729341219833,
            "Precio Gasolina 98 E5": 1.3267142836469914,
            "Precio Gasolina 95 E5": 1.2009083808036323,
            "Precio Biodiesel": 1.0900452508960579,
            "Precio Bioetanol": 1.280612903225806
        },
        "Aragón": {
            "Precio Gasoleo A": 1.0344076758398844,
            "Precio Gasoleo B": 0.7156634400289803,
            "Precio Gasoleo Premium": 1.118983288730264,
            "Precio Gasolina 95 E5": 1.1335198176514103,
            "Precio Gasolina 98 E5": 1.2647638824957157,
            "Precio Biodiesel": 1.0349556451612902,
            "Precio Gases licuados del petróleo": 0.5779550906083164
        },
        "Rioja (La)": {
            "Precio Gasoleo A": 1.0452535474051154,
            "Precio Gasoleo B": 0.7718433179723503,
            "Precio Gasoleo Premium": 1.1189204738967549,
            "Precio Gasolina 95 E5": 1.1383481266279305,
            "Precio Gasolina 98 E5": 1.2652185773716156,
            "Precio Biodiesel": 1.011306451612904,
            "Precio Gases licuados del petróleo": 0.5811612903225807
        },
        "Madrid": {
            "Precio Gases licuados del petróleo": 0.5917370427416251,
            "Precio Gasoleo A": 1.067197690164737,
            "Precio Gasoleo B": 0.7868444202461041,
            "Precio Gasoleo Premium": 1.13115185209629,
            "Precio Gasolina 95 E5": 1.1592895565355987,
            "Precio Gasolina 98 E5": 1.2853577613545482,
            "Precio Biodiesel": 1.099040322580645,
            "Precio Bioetanol": 1.202467741935484
        },
        "Murcia": {
            "Precio Gasoleo A": 1.0662846834308244,
            "Precio Gasoleo B": 0.7656170643491984,
            "Precio Gasoleo Premium": 1.140747549484226,
            "Precio Gasolina 95 E5": 1.176574613510658,
            "Precio Gasolina 98 E5": 1.3069604826805927,
            "Precio Gases licuados del petróleo": 0.5977686891961087,
            "Precio Biodiesel": 1.0929569892473119
        },
        "Navarra": {
            "Precio Gasoleo A": 1.0240734414333752,
            "Precio Gasoleo B": 0.7134617779050214,
            "Precio Gasoleo Premium": 1.1105380896286339,
            "Precio Gasolina 95 E5": 1.1293621991821725,
            "Precio Gasolina 98 E5": 1.261101726452472,
            "Precio Biodiesel": 0.9894368279569893,
            "Precio Gases licuados del petróleo": 0.5941157834101382
        },
        "Asturias": {
            "Precio Gasoleo A": 1.0913287406433527,
            "Precio Gasoleo B": 0.7853267917569193,
            "Precio Gasoleo Premium": 1.1602383662649973,
            "Precio Gasolina 95 E5": 1.193600872519625,
            "Precio Gasolina 98 E5": 1.3133444687957956,
            "Precio Gases licuados del petróleo": 0.6139569892473117,
            "Precio Biodiesel": 1.0728387096774192,
            "Precio Bioetanol": 1.3990000000000005
        },
        "Canarias": {
            "Precio Gasoleo A": 0.8424934169112304,
            "Precio Gasolina 95 E5": 0.9197971116755411,
            "Precio Gasolina 98 E5": 1.0159768706796677,
            "Precio Gasoleo Premium": 0.9122299697508282,
            "Precio Gases licuados del petróleo": 0.46756451612903227,
            "Precio Gasoleo B": 0.825
        },
        "Cantabria": {
            "Precio Gasoleo A": 1.0495880008883198,
            "Precio Gasoleo B": 0.7975260802841648,
            "Precio Gasoleo Premium": 1.1183240622457604,
            "Precio Gasolina 95 E5": 1.1444297799849497,
            "Precio Gasolina 98 E5": 1.2688693593062685,
            "Precio Biodiesel": 1.077274193548387,
            "Precio Gases licuados del petróleo": 0.6065833333333334
        },
        "Ceuta": {
            "Precio Gasoleo A": 0.8832473118279575,
            "Precio Gasolina 95 E5": 0.9632473118279571,
            "Precio Gasolina 98 E5": 0.9923584229390675,
            "Precio Gasoleo Premium": 0.9162903225806455
        },
        "Melilla": {
            "Precio Gasoleo A": 0.7720694789081883,
            "Precio Gasoleo Premium": 0.8271290322580648,
            "Precio Gasolina 95 E5": 0.8762873900293253
        }
    },
    "Noviembre": {
        "País Vasco": {
            "Precio Gasoleo A": 1.054938315013674,
            "Precio Gasoleo B": 0.7934994252873563,
            "Precio Gasoleo Premium": 1.1218544046428272,
            "Precio Gasolina 95 E5": 1.1524969680605486,
            "Precio Gasolina 98 E5": 1.2761176774240754,
            "Precio Biodiesel": 1.0547184273166443,
            "Precio Bioetanol": 1.3338055555555548,
            "Precio Gases licuados del petróleo": 0.5916476915644746,
            "Precio Gas Natural Comprimido": 0.989
        },
        "Castilla la Mancha": {
            "Precio Gasoleo A": 1.0806100352186296,
            "Precio Gasoleo B": 0.7331521719064898,
            "Precio Gasolina 95 E5": 1.182529805698238,
            "Precio Gasoleo Premium": 1.1582790089306483,
            "Precio Gasolina 98 E5": 1.3119863370110918,
            "Precio Gases licuados del petróleo": 0.6020624444444441,
            "Precio Gas Natural Comprimido": 0.9370000000000004,
            "Precio Biodiesel": 0.9971666666666664
        },
        "Comunidad Valenciana": {
            "Precio Gasoleo A": 1.0644562728805018,
            "Precio Gasoleo Premium": 1.1411002695236876,
            "Precio Gasolina 95 E5": 1.1762972904809297,
            "Precio Gasolina 98 E5": 1.3115067764368955,
            "Precio Gasoleo B": 0.7561698924312494,
            "Precio Gases licuados del petróleo": 0.5986197375947381,
            "Precio Biodiesel": 1.0198511904761907,
            "Precio Gas Natural Comprimido": 0.8709999999999998,
            "Precio Bioetanol": 1.2100333333333333
        },
        "Andalucia": {
            "Precio Gasoleo A": 1.0761969242716034,
            "Precio Gasoleo Premium": 1.1501193516347108,
            "Precio Gasolina 95 E5": 1.1885909074442786,
            "Precio Gasolina 98 E5": 1.317641027033815,
            "Precio Gasoleo B": 0.7479707512739917,
            "Precio Gases licuados del petróleo": 0.6037282989730919,
            "Precio Biodiesel": 1.0629029304029303
        },
        "Castilla y León": {
            "Precio Gasoleo A": 1.0608042776580242,
            "Precio Gasoleo B": 0.7667370679530765,
            "Precio Gasoleo Premium": 1.1324109801421185,
            "Precio Gasolina 95 E5": 1.1540736388415642,
            "Precio Gasolina 98 E5": 1.2785386054267431,
            "Precio Gases licuados del petróleo": 0.5992356691919192,
            "Precio Biodiesel": 1.0729873737373739
        },
        "Extremadura": {
            "Precio Gasoleo A": 1.0715787243519115,
            "Precio Gasoleo B": 0.7431692855006592,
            "Precio Gasoleo Premium": 1.1462690212714723,
            "Precio Gasolina 95 E5": 1.1747560317551362,
            "Precio Gasolina 98 E5": 1.3118827901742152,
            "Precio Gases licuados del petróleo": 0.5967375,
            "Precio Biodiesel": 1.0531499999999998
        },
        "Baleares": {
            "Precio Gasoleo A": 1.1251998697317995,
            "Precio Gasoleo Premium": 1.1899256218905476,
            "Precio Gasolina 95 E5": 1.2308961486758971,
            "Precio Gasolina 98 E5": 1.3575614873638997,
            "Precio Gases licuados del petróleo": 0.621630769230769,
            "Precio Gasoleo B": 0.8015882882882884
        },
        "Cataluña": {
            "Precio Gasoleo A": 1.0601081249537252,
            "Precio Gasoleo Premium": 1.144126048650339,
            "Precio Gasolina 95 E5": 1.1684137312671734,
            "Precio Gasolina 98 E5": 1.3077466607237571,
            "Precio Gases licuados del petróleo": 0.5779641206602225,
            "Precio Gasoleo B": 0.747585847066295,
            "Precio Biodiesel": 1.0481847670250894,
            "Precio Bioetanol": 1.3315000000000003,
            "Precio Gas Natural Comprimido": 0.7898416666666666
        },
        "Galicia": {
            "Precio Gases licuados del petróleo": 0.6115272927689592,
            "Precio Gasoleo A": 1.1016407811245648,
            "Precio Gasoleo B": 0.7863277071348376,
            "Precio Gasoleo Premium": 1.1678018313884417,
            "Precio Gasolina 98 E5": 1.3291731289058133,
            "Precio Gasolina 95 E5": 1.2037238037696807,
            "Precio Biodiesel": 1.0887666666666669,
            "Precio Bioetanol": 1.2769666666666666
        },
        "Aragón": {
            "Precio Gasoleo A": 1.0316657012170467,
            "Precio Gasoleo B": 0.7091902239363765,
            "Precio Gasoleo Premium": 1.1175597967217241,
            "Precio Gasolina 95 E5": 1.136482187685307,
            "Precio Gasolina 98 E5": 1.270134523456991,
            "Precio Biodiesel": 1.0262613095238093,
            "Precio Gases licuados del petróleo": 0.5803832362082361
        },
        "Rioja (La)": {
            "Precio Gasoleo A": 1.0395001612528023,
            "Precio Gasoleo B": 0.7674526455026457,
            "Precio Gasoleo Premium": 1.113639278531926,
            "Precio Gasolina 95 E5": 1.1389557563025214,
            "Precio Gasolina 98 E5": 1.2687494009866105,
            "Precio Biodiesel": 1.020233333333333,
            "Precio Gases licuados del petróleo": 0.580125
        },
        "Madrid": {
            "Precio Gases licuados del petróleo": 0.5837010597552792,
            "Precio Gasoleo A": 1.0606529371698201,
            "Precio Gasoleo B": 0.7798602763881703,
            "Precio Gasoleo Premium": 1.1250100858880951,
            "Precio Gasolina 95 E5": 1.158984431199035,
            "Precio Gasolina 98 E5": 1.2851905760818227,
            "Precio Biodiesel": 1.0941083333333335,
            "Precio Bioetanol": 1.2122666666666673
        },
        "Murcia": {
            "Precio Gasoleo A": 1.062331824802024,
            "Precio Gasoleo B": 0.7607000126918879,
            "Precio Gasolina 95 E5": 1.1787150341393355,
            "Precio Gasolina 98 E5": 1.30929552455962,
            "Precio Gasoleo Premium": 1.136018669258673,
            "Precio Gases licuados del petróleo": 0.5959134259259259,
            "Precio Biodiesel": 1.0726888888888884
        },
        "Navarra": {
            "Precio Gasoleo A": 1.0204767481076678,
            "Precio Gasoleo B": 0.7047266692522853,
            "Precio Gasoleo Premium": 1.1081188225165597,
            "Precio Gasolina 95 E5": 1.1290416786854047,
            "Precio Gasolina 98 E5": 1.2613446337229648,
            "Precio Biodiesel": 0.9855221031746028,
            "Precio Gases licuados del petróleo": 0.5898419312169314
        },
        "Asturias": {
            "Precio Gasoleo A": 1.0877957880824072,
            "Precio Gasoleo B": 0.7841069063516523,
            "Precio Gasoleo Premium": 1.1568616940785446,
            "Precio Gasolina 95 E5": 1.198247821856228,
            "Precio Gasolina 98 E5": 1.3176821508311651,
            "Precio Gases licuados del petróleo": 0.6070694444444446,
            "Precio Biodiesel": 1.0727666666666666,
            "Precio Bioetanol": 1.3990000000000005
        },
        "Canarias": {
            "Precio Gasoleo A": 0.8356393290722076,
            "Precio Gasolina 95 E5": 0.9072025087381774,
            "Precio Gasolina 98 E5": 1.003431309511188,
            "Precio Gasoleo Premium": 0.9053242365353155,
            "Precio Gases licuados del petróleo": 0.4833750000000003
        },
        "Cantabria": {
            "Precio Gasoleo A": 1.0492970185838446,
            "Precio Gasoleo B": 0.7925583027859238,
            "Precio Gasoleo Premium": 1.1175756651294215,
            "Precio Gasolina 95 E5": 1.1492895206319105,
            "Precio Gasolina 98 E5": 1.2708673990391335,
            "Precio Biodiesel": 1.0850666666666664,
            "Precio Gases licuados del petróleo": 0.6046000000000001
        },
        "Ceuta": {
            "Precio Gasoleo A": 0.8719296296296294,
            "Precio Gasolina 95 E5": 0.9530777777777772,
            "Precio Gasolina 98 E5": 0.9823259259259258,
            "Precio Gasoleo Premium": 0.9054200000000007
        },
        "Melilla": {
            "Precio Gasoleo A": 0.7646128205128208,
            "Precio Gasoleo Premium": 0.8159238095238093,
            "Precio Gasolina 95 E5": 0.8655969696969698,
            "Precio Gasolina 98 E5": 0.8443333333333336
        }
    },
    "Diciembre": {
        "País Vasco": {
            "Precio Gasoleo A": 0.9826721035960551,
            "Precio Gasoleo B": 0.7296850886950412,
            "Precio Gasoleo Premium": 1.0503904512740625,
            "Precio Gasolina 95 E5": 1.1275106060690667,
            "Precio Gasolina 98 E5": 1.251372085145625,
            "Precio Biodiesel": 0.9863513193748746,
            "Precio Bioetanol": 1.32894623655914,
            "Precio Gases licuados del petróleo": 0.5749199751861045,
            "Precio Gas Natural Comprimido": 0.9238387096774192
        },
        "Castilla la Mancha": {
            "Precio Gasoleo A": 1.0172211739351562,
            "Precio Gasoleo B": 0.6810530136832545,
            "Precio Gasolina 95 E5": 1.1590189222160399,
            "Precio Gasoleo Premium": 1.0934629509245934,
            "Precio Gasolina 98 E5": 1.2868182080675055,
            "Precio Gases licuados del petróleo": 0.5853121588089328,
            "Precio Gas Natural Comprimido": 0.9120537634408601,
            "Precio Biodiesel": 0.9720000000000001
        },
        "Comunidad Valenciana": {
            "Precio Gasoleo A": 0.9998393718193268,
            "Precio Gasoleo Premium": 1.0756404975686649,
            "Precio Gasolina 95 E5": 1.153295833411686,
            "Precio Gasolina 98 E5": 1.2873868338049643,
            "Precio Gasoleo B": 0.7064041818642992,
            "Precio Gases licuados del petróleo": 0.579207449384869,
            "Precio Biodiesel": 0.974828341013825,
            "Precio Gas Natural Comprimido": 0.8709999999999997,
            "Precio Bioetanol": 1.1890967741935488
        },
        "Andalucia": {
            "Precio Gasoleo A": 1.009143034517231,
            "Precio Gasoleo Premium": 1.0824642457197955,
            "Precio Gasolina 95 E5": 1.1655815618551215,
            "Precio Gasolina 98 E5": 1.2934423240296273,
            "Precio Gasoleo B": 0.6923828835190415,
            "Precio Gases licuados del petróleo": 0.5841927853340048,
            "Precio Biodiesel": 1.0242332506203478,
            "Precio Gas Natural Comprimido": 0.8459999999999999
        },
        "Castilla y León": {
            "Precio Gasoleo A": 0.9907695826110188,
            "Precio Gasoleo B": 0.7081349158148907,
            "Precio Gasoleo Premium": 1.0615775448044222,
            "Precio Gasolina 95 E5": 1.1263747856524904,
            "Precio Gasolina 98 E5": 1.2520412066803885,
            "Precio Gases licuados del petróleo": 0.58227658343396,
            "Precio Biodiesel": 1.020904838709677
        },
        "Extremadura": {
            "Precio Gasoleo A": 1.0093849324530646,
            "Precio Gasoleo B": 0.6976336945019371,
            "Precio Gasoleo Premium": 1.081882641802213,
            "Precio Gasolina 95 E5": 1.151630512768105,
            "Precio Gasolina 98 E5": 1.288244799062267,
            "Precio Gases licuados del petróleo": 0.5782338709677419,
            "Precio Biodiesel": 0.9970483870967741
        },
        "Baleares": {
            "Precio Gasoleo A": 1.0461166669684423,
            "Precio Gasoleo Premium": 1.1117099021023915,
            "Precio Gasolina 95 E5": 1.2041065905139126,
            "Precio Gasolina 98 E5": 1.3315580823084237,
            "Precio Gases licuados del petróleo": 0.5961066997518608,
            "Precio Gasoleo B": 0.7230854402789886
        },
        "Cataluña": {
            "Precio Gasoleo A": 0.9930384690424703,
            "Precio Gasoleo Premium": 1.076160871361601,
            "Precio Gasolina 95 E5": 1.1436347375781812,
            "Precio Gasolina 98 E5": 1.2828351323171205,
            "Precio Gases licuados del petróleo": 0.5594093173931005,
            "Precio Gasoleo B": 0.6946882692442997,
            "Precio Biodiesel": 0.9976024973985432,
            "Precio Bioetanol": 1.3219032258064518,
            "Precio Gas Natural Comprimido": 0.7847403225806447
        },
        "Galicia": {
            "Precio Gases licuados del petróleo": 0.5937629255451836,
            "Precio Gasoleo A": 1.0288563090596097,
            "Precio Gasoleo B": 0.7297333034740097,
            "Precio Gasoleo Premium": 1.098033190547838,
            "Precio Gasolina 98 E5": 1.3018233851625205,
            "Precio Gasolina 95 E5": 1.1769733424093767,
            "Precio Biodiesel": 1.0384072580645158,
            "Precio Bioetanol": 1.2486774193548387
        },
        "Aragón": {
            "Precio Gasoleo A": 0.9636292225158624,
            "Precio Gasoleo B": 0.6537584524127852,
            "Precio Gasoleo Premium": 1.046080284034902,
            "Precio Gasolina 95 E5": 1.112255415707533,
            "Precio Gasolina 98 E5": 1.2447829433047422,
            "Precio Biodiesel": 0.9673571428571427,
            "Precio Gases licuados del petróleo": 0.5681528874351457
        },
        "Rioja (La)": {
            "Precio Gasoleo A": 0.9693901871836222,
            "Precio Gasoleo B": 0.7056596951435659,
            "Precio Gasoleo Premium": 1.039409365056196,
            "Precio Gasolina 95 E5": 1.1129732747376653,
            "Precio Gasolina 98 E5": 1.237507697660082,
            "Precio Biodiesel": 0.972033333333333,
            "Precio Gases licuados del petróleo": 0.5746290322580646
        },
        "Madrid": {
            "Precio Gases licuados del petróleo": 0.5666308833446401,
            "Precio Gasoleo A": 0.9889231301038559,
            "Precio Gasoleo B": 0.7164967026766719,
            "Precio Gasoleo Premium": 1.0529178481088666,
            "Precio Gasolina 95 E5": 1.1341104877367385,
            "Precio Gasolina 98 E5": 1.2619473619698234,
            "Precio Biodiesel": 1.0150026881720433,
            "Precio Bioetanol": 1.1904838709677414,
            "Precio Gas Natural Comprimido": 0.8056071428571426
        },
        "Murcia": {
            "Precio Gasoleo A": 0.9933170486522644,
            "Precio Gasoleo B": 0.7062128545056593,
            "Precio Gasoleo Premium": 1.0667275422735254,
            "Precio Gasolina 95 E5": 1.1558947153369519,
            "Precio Gasolina 98 E5": 1.2842497209879098,
            "Precio Gases licuados del petróleo": 0.5714336917562726,
            "Precio Biodiesel": 1.0153440860215048,
            "Precio Gas Natural Comprimido": 0.8459999999999999
        },
        "Navarra": {
            "Precio Gasoleo A": 0.9537409819403763,
            "Precio Gasoleo B": 0.6469817786402461,
            "Precio Gasoleo Premium": 1.0414189714450908,
            "Precio Gasolina 95 E5": 1.102285347078222,
            "Precio Gasolina 98 E5": 1.23612551559632,
            "Precio Biodiesel": 0.9486159754224269,
            "Precio Gases licuados del petróleo": 0.5783831541218636
        },
        "Asturias": {
            "Precio Gasoleo A": 1.0200088032629564,
            "Precio Gasoleo B": 0.7285457450833952,
            "Precio Gasoleo Premium": 1.0889239658851895,
            "Precio Gasolina 95 E5": 1.175355726227717,
            "Precio Gasolina 98 E5": 1.295702280794328,
            "Precio Gases licuados del petróleo": 0.5899758064516128,
            "Precio Biodiesel": 0.986822580645161,
            "Precio Bioetanol": 1.3696666666666677
        },
        "Canarias": {
            "Precio Gasoleo A": 0.8148317428175571,
            "Precio Gasolina 95 E5": 0.8984467906753814,
            "Precio Gasolina 98 E5": 0.9955288783125948,
            "Precio Gasoleo Premium": 0.8828768289800032,
            "Precio Gases licuados del petróleo": 0.488910138248848
        },
        "Cantabria": {
            "Precio Gasoleo A": 0.9824062808231047,
            "Precio Gasoleo B": 0.7494163473969667,
            "Precio Gasoleo Premium": 1.0505611128644974,
            "Precio Gasolina 95 E5": 1.1268115905566898,
            "Precio Gasolina 98 E5": 1.2502939781091766,
            "Precio Biodiesel": 1.0094419354838708,
            "Precio Gases licuados del petróleo": 0.5914799608993155
        },
        "Ceuta": {
            "Precio Gasoleo A": 0.8283978494623662,
            "Precio Gasolina 95 E5": 0.939494623655914,
            "Precio Gasolina 98 E5": 0.9730501792114695,
            "Precio Gasoleo Premium": 0.8608580645161296
        },
        "Melilla": {
            "Precio Gasoleo A": 0.7199999999999998,
            "Precio Gasoleo Premium": 0.7725806451612901,
            "Precio Gasolina 95 E5": 0.8640087976539591
        }
    }
}